Workbook

Sheet ReadMe
A1: Interpreting the Russian Operations Against Europe Event Dataset
A2: 1 | B2: Event data collected on (attempted) sabotage, attacks & influence campaigns in the physical domain, or with a clear effect on a physical object / service / person.
A3: 2 | B3: As a result, cyber operations were largely left out of consideration, as hundreds if not thousands of incidents too many to tally in time available; only included when physical effect / consequence present (e.g., disruption of water works).
A4: 3 | B4: In many cases, attribution is difficult. We have erred on the side of caution, leaving out numerous incidents and suspicious accidents where suspicion of Russian involvement was too tenous (see Excluded).
A5: 4 | B5: We included cases when they a) were linked to Russia by the authorities / politicians, and / or b) appeared to fit in a pattern of similar attacks / events that had been 'officially' suspected of being linked to Russia, and / or c) where based on journalistic investigations that had uncovered hard evidence of a link to Russia (e.g., status reports to handlers, details of financial transactions, etc.)
A6: 5 | B6: The event data anly covers incidents initiated in the time period since the Russian invasion of Ukraine (February 2022).
A7: 6 | B7: The 'IncidentYear' field records the year when a particular operation was carried out, or an ongoing activity begun. It does not record the year of the publication in which the incident was reported.
A8: 7 | B8: Event data focuses solely on Europe, in particular European Union member states.
A9: 8 | B9: Only events ostensibly linked to the 2022 Russian invasion of Ukraine are recorded. This means that incidents such as the intimidation of Russian opposition members abroad, or espionage that cannot clearly be linked specifically to the invasion of Ukraine (e.g., espionage to prepare for sabotage against a country supporting Ukraine), are excluded.
A10: 9 | B10: Despite our best efforts and precautions, this event data should be treated as speculative, likely to be incomplete (underreporting the total number of incidents) and subject to change.
A11: 10 | B11: The primary purpose of this event data is to help inform the public debate on Russia's increasingly aggressive operations in Europe following its invasion of Ukraine by providing an overview of events & attacks related to the physical domain.
A13: Version: | B13: 46034
A14: Dataset repository | B14: https://doi.org/10.7910/DVN/TQ0FMQ
A15: Copyright: | B15: Dr. Bart Schuurman, Professor of Terrorism and Political Violence, Leiden University
A16: Contact: | B16: b.w.schuurman@fgga.leidenuniv.nl
A17: License: | B17: CC BY 4.0
A19: Acknowledgements: | B19: Maurits Huijbens, Dion Jordens, and Stijn Willem van 't Land assisted with data collection and validation. This project was supported by subsidy #3985535, awarded by the Dutch Minstry of Justice and Security in June 2022.
A20: Project website: | B20: https://bewakenenbeveiligen.universiteitleiden.nl/about
A22: Categories used
A23: Type of incident
A24: Sabotage | B24: Degrading or destroying infrastructure or facilities for political, economic or military advantage. Includes attempted and planned sabotage.
A25: Vandalism | B25: Deliberate destruction or damage to public or private property, here intended to serve political purposes such as sowing fear or chaos.
A26: Influence operation | B26: Campaigns or actions intended to influence the (political) views of European citizens or politicians, here with the aim of undermining support for Ukraine or destabilizing domestic / EU politics.
A27: Assassination | B27: Murder for political reasons. Includes plots and attempts.
A28: Disruptive immigration | B28: Deliberately creating large and/or enduring immigration / refugee flows towards EU member states' borders.
A29: Terrorism | B29: Deliberate use of deadly violence against civilian targets (e.g., transport aircraft) with the aim of influencing larger audiences beyond those targeted in furtherance of a political cause, e.g., to intimidate or inspire.
A30: Disruption | B30: (Attempted) disruption of (public) services, such as the operation of airports, without physical destruction of said services as would often be the case for sabotage.
A31: Arson | B31: (Attempted) desctruction of property through arson.
A32: Reconnaissance | B32: Gathering of information on critical infrastructure, potentially as preparation for sabotage.
A34: Apparent goal
A35: Dissuade defection | B35: Stop people from defecting from the Russian armed forces / state by demonstrating the potential costs (e.g., being killed) of doing so.
A36: Kill politician / head of state | B36: As described.
A37: Degrade military infrastructure | B37: Damaging or destroying military facilities / equipment.
A38: Disrupt (civil) aviation | B38: Interfering with the ability of (civil) aviation to operate safely, e.g. through GPS jamming or flying drones over airpots.
A39: Compromise public utilities | B39: Damaging or destroying public utilities such as water treatment plants, or engaging in preparations to do so.
A40: Degrade energy supply / commmunciations infrastructure | B40: Damageing or destroying the facilities or infrastructure involved in the provision of energy or enabling telecommunications, or engaging in preparations to do so (e.g., undersea cables).
A41: Compromise domestic / EU politics | B41: Attempts to influence politicians, political parties, or public opinion regarding politics such that pro-Russian voices become stronger, and / or support for Ukraine is undermined.
A42: Inflict economic damage | B42: Damaging or destroying buildings / facilities / infrastructure / services with the aim of causing economic damage.
A43: Disrupt (military) aid to Ukraine | B43: Physically degrading the ability of EU states to deliver aid to Ukraine (e.g., sabotating railroads) and / or underming public / political opinion such that aid for Ukraine is negatively affected.
A44: Disrupt daily life | B44: Attempts to influence EU citizen's daily life by damaging or destroying publc property / services, and / or spreading confusion / chaos among citizens with unexpected and stressful events such as vandalism, arson, intimidating displays.
A45: Intimidate politician / journalist | B45: (Attempted) intimidation of politician(s) or journalist(s).
A46: Preparation for potential sabotage | B46: Where the goal appears to be gathering information that can be used at a later date to carry out sabotage operations (e.g., using drones to map critical infrastructure).
A48: Type of target
A49: Arms deliveries to Ukraine | B49: Production, shipment, or storage of weapons and military materiel intended for the Urkainian armed forces in their war against the Russian invaders.
A50: Border | B50: Borders between European countries and Russia / Belarus.
A51: Civil aviation | B51: Airplanes / airports used for the transportation of goods and or passengers.
A52: Transport infrastructure | B52: Warehouses, railways, roads, buses, trains, etc.
A53: Shopping center / Public space / Memorial / Landmark | B53: As described.
A54: Energy / communications infrastructure | B54: Power cables, power plants, internet cables, data centers, etc. (including underseas).
A55: Military / weapons production infrastructure | B55: Military bases, military materiel (e.g., planes, helicopters, tanks), arms production facilities, weapons storage sites, etc.
A56: Politician(s) | B56: European politicians or Russian opposition figures.
A57: Journalist(s) | B57: As described.
A58: Defector(s) | B58: Russian military personnel who have defected.
A59: Industrialist(s) | B59: CEOs of weapons production companies.

Sheet EventData
A1: IncidentYear | B1: IncidentMonth | C1: IncidentDateRange | D1: IncidentDateStart | E1: IncidentDateEnd | F1: What | G1: Where | H1: EventCategory | I1: EventCategory2 | J1: ApparentGoal1 | K1: ApparentGoal2 | L1: TargetType | M1: TargetType2 | N1: DisposableAgentsInvolved | O1: For discussion | P1: Note
A2: 2022 | B2: January | C2: Yes | D2: 44562 | E2: 44926 | F2: Ongoing attempt to map offshore comms/energy infrastructure in North Sea / Baltic | G2: North Sea; Baltic Sea | H2: Reconnaissance | I2: Does not apply | J2: Preparation for potential sabotage | K2: Does not apply | L2: Energy / communications infrastructure | M2: Does not apply | O2: No | P2: Ongoing for years.
A3: 2022 | B3: March | C3: Yes | D3: 44621 | E3: 44803 | F3: Following Ru invasion, Marsalek-led Bulgarian spyring began a disinfo operation in Austria and Germany with stickers and graffiti. | G3: Austria; Germany | H3: Influence operation | I3: Does not apply | J3: Disrupt (military) aid to Ukraine | K3: Does not apply | L3: Public space: Shopping centre / Memorial / Landmark / Company / School | M3: Does not apply | N3: Yes | O3: No | P3: One of several operations conducted by the Bulgarian spy ring that was arrested in the UK in early 2023. Start and end-date not certain, but began shortly after invasion of Ukraine and seem to have ended by September, when new targets came into view.
A4: 2022 | B4: April | C4: No | D4: DNA | E4: DNA | F4: Spraypainting 'KILLNET HACKED YOU' on Cyber Defence Centre, Tallinn | G4: Estonia | H4: Vandalism | I4: Does not apply | J4: Disrupt daily life | K4: Does not apply | L4: Military / weapons production infrastructure | M4: Does not apply | O4: No
A5: 2022 | B5: April | C5: No | D5: DNA | E5: DNA | F5: Pro-Russian rallies / protest / vehicle parades in various European cities. Various experts suggest likely (partly) result of top-down pressure on Russian expats. | G5: Germany; Greece; Ireland; Cyprus | H5: Influence operation | I5: Does not apply | J5: Disrupt (military) aid to Ukraine | K5: Does not apply | L5: Public space: Shopping centre / Memorial / Landmark / Company / School | M5: Does not apply | N5: Unknown | O5: No
A6: 2022 | B6: May | C6: No | D6: DNA | E6: DNA | F6: Spionage of Lielvarde military airfield, near Rembate, Latvia | G6: Latvia | H6: Reconnaissance | I6: Does not apply | J6: Preparation for potential sabotage | K6: Does not apply | L6: Military / weapons production infrastructure | M6: Does not apply | O6: No
A7: 2022 | B7: May | C7: Yes | D7: 44682 | E7: 44926 | F7: Operation Doppelganger: Russian influence campaign that used faked websites (e.g., Der Spiegel, WaPo) to undermine Western support for Ukraine. Social Design Agency. Part of 'Comprehensive Counter Campaign' | G7: Germany; France; United Kingdom; Italy; United States; Ukraine; Latvia; Poland; The Netherlands | H7: Influence operation | I7: Does not apply | J7: Compromise domestic / EU politics | K7: Does not apply | L7: Internet / Social media / News | M7: Does not apply | O7: No | P7: See also: https://mpf.se/psychological-defence-agency/publications/archive/2025-05-15-beyond-operation-doppelganger-a-capability-assessment-of-the-social-design-agency
A8: 2022 | B8: June | C8: Yes | D8: 44713 | E8: 44926 | F8: Children of war campaign (Kinder des Krieges). Kremlin-backed and AFD supported campaign to sway public opinion against supporting Ukraine. | G8: Germany | H8: Influence operation | I8: Does not apply | J8: Disrupt (military) aid to Ukraine | K8: Does not apply | L8: Public space: Shopping centre / Memorial / Landmark / Company / School | M8: Does not apply | N8: No | O8: No
A9: 2022 | B9: July | C9: No | D9: DNA | E9: DNA | F9: Arms factory fire / explosion in Karnobat, Bulgaria 2022 | G9: Bulgaria | H9: Sabotage | I9: Does not apply | J9: Disrupt (military) aid to Ukraine | K9: Does not apply | L9: Military / weapons production infrastructure | M9: Does not apply | O9: No
A10: 2022 | B10: September | C10: Yes | D10: 44805 | E10: 44926 | F10: Building (far) left & (far) right-wing anti-war coaltion in Germany (Wagenknecht / AfD) | G10: Germany | H10: Influence operation | I10: Does not apply | J10: Disrupt (military) aid to Ukraine | K10: Compromise domestic / EU politics | L10: Politician(s) | M10: Does not apply | O10: No
A11: 2022 | B11: September | C11: Yes | D11: 44805 | E11: 44865 | F11: Russian nationals flying drones over Norwegian airports, energy infrastructure, photographing | G11: Norway | H11: Reconnaissance | I11: Disruption | J11: Preparation for potential sabotage | K11: Disrupt (civil) aviation | L11: Energy / communications infrastructure | M11: Civil aviation | O11: No
A12: 2022 | B12: October | C12: Yes | D12: 44835 | E12: 44926 | F12: Plot to use IMSI catchers to identify and locate Ukrainian soldiers training to operate Patriot missile batteries, to use as targeting information. Base being targeted was Patch Barracks near Stuttgart. Plot developed in UK. | G12: United Kingdom; Germany | H12: Reconnaissance | I12: Does not apply | J12: Preparation for potential sabotage | K12: Does not apply | L12: Military / weapons production infrastructure | M12: Does not apply | N12: Yes | O12: No | P12: Plot carried on until early 2023 but recorded in 2022 to avoid double-counting. One of several operations conducted by the Bulgarian spy ring that was arrested in the UK in early 2023.
A13: 2022 | B13: November | C13: Yes | D13: 44866 | E13: 44926 | F13: Six letter bombs sent to targets in Spain in Nov & Dec. Targeted Prime Minister, US & UKR embassies, defence ministry, arms manufacturer. Russian Imperial Movement suspected, acting on behalf of Ru intel | G13: Spain | H13: Terrorism | I13: Does not apply | J13: Disrupt (military) aid to Ukraine | K13: Does not apply | L13: Politician(s) / Official(s) | M13: Military / weapons production infrastructure | N13: No | O13: No | P13: Goal seems to be to signal intent / capability. But that could be argued for all of these operations. Going with undermining support for Ukraine as overarching motivation.
A14: 2022 | B14: December | C14: No | D14: DNA | E14: DNA | F14: Russian agents provocateur use two demonstrations in Paris to spread anti-Ukrainian propaganda. Presenting a protest about something else entirely as being against Western support for Ukraine. | G14: France | H14: Influence operation | I14: Does not apply | J14: Disrupt (military) aid to Ukraine | K14: Does not apply | L14: Public space: Shopping centre / Memorial / Landmark / Company / School | M14: Does not apply | N14: Unknown | O14: No | P14: Grouped these demonstrations by country / year. Not listing each demonstration individually.
A15: 2023 | B15: January | C15: Yes | D15: 44927 | E15: 45291 | F15: Building (far) left & (far) right-wing anti-war coaltion in Germany (Wagenknecht / AfD) | G15: Germany | H15: Influence operation | I15: Does not apply | J15: Disrupt (military) aid to Ukraine | K15: Compromise domestic / EU politics | L15: Politician(s) | M15: Does not apply | O15: No
A16: 2023 | B16: January | C16: Yes | D16: 44927 | E16: 45046 | F16: Russian agents provocateur use demonstrations across Europe to spread anti-Ukrainian propaganda. Presenting a protest about something else entirely as being against Western support for Ukraine. | G16: The Netherlands; Belgium; France; Spain | H16: Influence operation | I16: Does not apply | J16: Disrupt (military) aid to Ukraine | K16: Does not apply | L16: Public space: Shopping centre / Memorial / Landmark / Company / School | M16: Does not apply | N16: Unknown | O16: No
A17: 2023 | B17: January | C17: Yes | D17: 44927 | E17: 45291 | F17: Operation Doppelganger: Russian influence campaign that used faked websites (e.g., Der Spiegel, WaPo) to undermine Western support for Ukraine. Social Design Agency. Part of 'Comprehensive Counter Campaign' | G17: Germany; France; United Kingdom; Italy; United States; Ukraine; Latvia; Poland; The Netherlands | H17: Influence operation | I17: Does not apply | J17: Compromise domestic / EU politics | K17: Does not apply | L17: Internet / Social media / News | M17: Does not apply | O17: No | P17: See also: https://mpf.se/psychological-defence-agency/publications/archive/2025-05-15-beyond-operation-doppelganger-a-capability-assessment-of-the-social-design-agency
A18: 2023 | B18: January | C18: Yes | D18: 44927 | E18: 45291 | F18: Ongoing attempt to map offshore comms/energy infrastructure in North Sea / Baltic | G18: North Sea; Baltic Sea | H18: Reconnaissance | I18: Does not apply | J18: Preparation for potential sabotage | K18: Does not apply | L18: Energy / communications infrastructure | M18: Does not apply | O18: No | P18: Ongoing for years.
A19: 2023 | B19: January | C19: Yes | D19: 44927 | E19: 45291 | F19: Monthly 'Peace demonstations' on the Dam in Amsterdam. Monthly since approximately the Russian invasion of Ukraine in 2022. Organized by Dutch peace activists, but supported & financed by Russian organizations. | G19: The Netherlands | H19: Influence operation | I19: Does not apply | J19: Disrupt (military) aid to Ukraine | K19: Does not apply | L19: Public space: Shopping centre / Memorial / Landmark / Company / School | M19: Does not apply | N19: No | O19: No | P19: Appear to have begun in 2023 and to be ongoing in 2025. See: https://kyivindependent.com/who-is-behind-pro-russian-stop-zelensky-demonstrations-in-europe/
A20: 2023 | B20: January | C20: Yes | D20: 44927 | E20: 45291 | F20: Children of war campaign (Kinder des Krieges). Kremlin-backed and AFD supported campaign to sway public opinion against supporting Ukraine. | G20: Germany | H20: Influence operation | I20: Does not apply | J20: Disrupt (military) aid to Ukraine | K20: Does not apply | L20: Public space: Shopping centre / Memorial / Landmark / Company / School | M20: Does not apply | N20: No | O20: No
A21: 2023 | B21: January | C21: No | D21: DNA | E21: DNA | F21: Explosives cache found near NATO pipeline in Germany | G21: Germany | H21: Sabotage (preparation) | I21: Does not apply | J21: Degrade military infrastructure | K21: Does not apply | L21: Military / weapons production infrastructure | M21: Does not apply | O21: No | P21: May 2024 reporting cites security sources saying the cache was likely prepared 12 to 18 months ago. Taking average of 15 months as starting point, i.e. January 2023.
A22: 2023 | B22: January | C22: Yes | D22: 44927 | E22: 45016 | F22: Attempt to sabotage arms deliveries to Ukraine in Poland, plant cameras, recruit Ukrainian refugees | G22: Poland | H22: Sabotage (preparation) | I22: Does not apply | J22: Disrupt (military) aid to Ukraine | K22: Does not apply | L22: Transport infrastructure | M22: Does not apply | O22: No | P22: See this source for timing the start of this operation to at least January 2023: https://www.pap.pl/aktualnosci/ekspert-ludzie-czasem-nawet-nie-wiedza-ze-dzialaja-na-zlecenie-rosjan
A23: 2023 | B23: March | C23: No | D23: DNA | E23: DNA | F23: Arms factory fire / explosion in Karnobat, Bulgaria 2023 | G23: Bulgaria | H23: Sabotage | I23: Does not apply | J23: Disrupt (military) aid to Ukraine | K23: Does not apply | L23: Military / weapons production infrastructure | M23: Does not apply | O23: No
A24: 2023 | B24: March | C24: Yes | D24: 44986 | E24: 45291 | F24: Voice of Europe, cash payments to anti-establishment politicians, Russian attempt to influence EU Parliament elections | G24: Germany;Belgium;France;Czechia;Netherlands; | H24: Influence operation | I24: Does not apply | J24: Compromise domestic / EU politics | K24: Disrupt (military) aid to Ukraine | L24: Politician(s) | M24: Does not apply | O24: No | P24: See Wiki for details on period of operation: https://en.wikipedia.org/wiki/Voice_of_Europe#:~:text=The%20organization%20allegedly%20funneled%20up,candidates%20in%20European%20Parliament%20elections.
A25: 2023 | B25: May | C25: No | D25: DNA | E25: DNA | F25: Descecration of Sinimäed and Narva-Jõesuu memorial sites Estonia | G25: Estonia | H25: Vandalism | I25: Does not apply | J25: Disrupt daily life | K25: Does not apply | L25: Memorial sites / Landmarks | M25: Does not apply | N25: Yes
A26: 2023 | B26: June | C26: Yes | D26: 45078 | E26: 45291 | F26: Portal Kombat / Pravda network: websites disseminating pro-Russian content on war in Ukraine to Western audiences (ongoing) | G26: France; Germany; Austria; Switzerland; Poland; Spain; United Kingdom; United States | H26: Influence operation | I26: Does not apply | J26: Compromise domestic / EU politics | K26: Does not apply | L26: Internet / Social media / News | M26: Does not apply | O26: No
A27: 2023 | B27: July | C27: No | D27: DNA | E27: DNA | F27: Sweden targeted by Russia-backed disinformation campaign to undermine its NATO membership, claims that Sweden supports burning Quran | G27: Sweden | H27: Influence operation | I27: Does not apply | J27: Compromise domestic / EU politics | K27: Does not apply | L27: Internet / Social media / News | M27: Does not apply | O27: No
A28: 2023 | B28: August | C28: Yes | D28: 45139 | E28: 45291 | F28: GPS jamming & spoofing over Baltic Sea. As well as near Black Sea | G28: Baltic Sea; Finland; Latvia; Lithuania; Poland; Romania; Bulgaria | H28: Disruption | I28: Does not apply | J28: Disrupt (civil) aviation | K28: Does not apply | L28: Civil aviation | M28: Does not apply | O28: No
A29: 2023 | B29: August | C29: Yes | D29: 45139 | E29: 45199 | F29: Sending illegal immigrants towards Latvia: through Belarus. Appears to have been a peak in these months that was likely orchestrated. | G29: Latvia | H29: Disruptive immigration | I29: Does not apply | J29: Disrupt daily life | K29: Does not apply | L29: Border | M29: Does not apply | O29: No
A30: 2023 | B30: September | C30: Yes | D30: 45170 | E30: 45291 | F30: Pro-Russian campaign to influence 2024 EU parliamentary elections by Jean-Luc Schaffhauser | G30: France | H30: Influence operation | I30: Does not apply | J30: Compromise domestic / EU politics | K30: Disrupt (military) aid to Ukraine | L30: Politician(s) | M30: Does not apply | O30: No
A31: 2023 | B31: October | C31: No | D31: DNA | E31: DNA | F31: Gas & telecom cables Finland - Estonia damaged / NewNew Polar Bear incident | G31: Baltic Sea | H31: Sabotage | I31: Does not apply | J31: Degrade energy supply / communications infrastructure | K31: Does not apply | L31: Energy / communications infrastructure | M31: Does not apply | O31: No
A32: 2023 | B32: October | C32: Yes | D32: 45200 | E32: 45291 | F32: Russians amplify 'bed bug' panic on social media, Paris, France, fall 2023 | G32: France | H32: Influence operation | I32: Does not apply | J32: Disrupt daily life | K32: Does not apply | L32: Internet / Social media / News | M32: Does not apply | O32: No
A33: 2023 | B33: October | C33: No | D33: DNA | E33: DNA | F33: Hundreds of bomb threats emailed to schools in the Latvia, Estonia, Lithuania. Messages in Russian. Lithuanian security service sees 'hostile states' behind it. | G33: Estonia; Latvia; Lithuania | H33: Terrorism | I33: Does not apply | J33: Disrupt daily life | K33: Does not apply | L33: Public space: Shopping centre / Memorial / Landmark / Company / School | M33: Does not apply | O33: Yes | P33: Although Russia not directly named, link to hostile state made in public and fits pattern. Bomb threats seen as threat of violence against civilians, hence treated as terrorism.
A34: 2023 | B34: November | C34: No | D34: DNA | E34: DNA | F34: Stars of David graffiti in Paris, suspected Russian influence op | G34: France | H34: Vandalism | I34: Does not apply | J34: Disrupt daily life | K34: Does not apply | L34: Public space: Shopping centre / Memorial / Landmark / Company / School | M34: Does not apply | O34: No
A35: 2023 | B35: November | C35: Yes | D35: 45139 | E35: 45291 | F35: Russia sends large number immigrants towards Finish border | G35: Finland | H35: Disruptive immigration | I35: Does not apply | J35: Disrupt daily life | K35: Does not apply | L35: Border | M35: Does not apply | O35: No | P35: Apparently the flow of migrants stopped after Finland closed its border with Russia at the end of 2023: https://www.reuters.com/world/europe/finnish-government-seeks-extend-ban-migrants-seeking-asylum-russia-border-2025-03-27/
A36: 2023 | B36: November | C36: No | D36: DNA | E36: DNA | F36: Sending illegal immigrants towards Estonia. No reporting to suggest this particular spike persisted for very long. | G36: Estonia | H36: Disruptive immigration | I36: Does not apply | J36: Disrupt daily life | K36: Does not apply | L36: Border | M36: Does not apply | O36: No
A37: 2023 | B37: December | C37: No | D37: DNA | E37: DNA | F37: Vandalizing car of Estonian interior minister | G37: Estonia | H37: Vandalism | I37: Does not apply | J37: Intimidate politician / journalist | K37: Does not apply | L37: Politician(s) | M37: Does not apply | O37: No
A38: 2023 | B38: December | C38: No | D38: DNA | E38: DNA | F38: Vandalizing car of Estonian journalist | G38: Estonia | H38: Vandalism | I38: Does not apply | J38: Intimidate politician / journalist | K38: Does not apply | L38: Journalist(s) | M38: Does not apply | O38: No
A39: 2024 | B39: January | C39: No | D39: DNA | E39: DNA | F39: Sending illegal immigrants towards Finland. Coded as 1 month incident as unclear whether this persisted, see also link at end of entry. | G39: Finland | H39: Disruptive immigration | I39: Does not apply | J39: Disrupt daily life | K39: Does not apply | L39: Border | M39: Does not apply | O39: No | P39: https://www.reuters.com/world/europe/finnish-government-seeks-extend-ban-migrants-seeking-asylum-russia-border-2025-03-27/
A40: 2024 | B40: January | C40: No | D40: DNA | E40: DNA | F40: Arson attempt on paint factory / fuel depot Wroclaw, Poland | G40: Poland | H40: Arson | I40: Does not apply | J40: Inflict economic damage | K40: Does not apply | L40: Energy / communications infrastructure | M40: Does not apply | O40: No | P40: Further details: https://notesfrompoland.com/2025/02/21/poland-jails-ukrainian-for-eight-years-for-preparing-sabotage-on-behalf-of-russia/
A41: 2024 | B41: January | C41: Yes | D41: 45292 | E41: 45473 | F41: Pro-Russian campaign to influence 2024 EU parliamentary elections by Jean-Luc Schaffhauser | G41: France | H41: Influence operation | I41: Does not apply | J41: Compromise domestic / EU politics | K41: Disrupt (military) aid to Ukraine | L41: Politician(s) | M41: Does not apply | O41: No
A42: 2024 | B42: January | C42: No | D42: DNA | E42: DNA | F42: Monument to Lithuanian partisan leader Adolfas Ramanauskas-Vanagas in Merkiné defaced with paint | G42: Lithuania | H42: Vandalism | I42: Does not apply | J42: Disrupt daily life | K42: Does not apply | L42: Public space: Shopping centre / Memorial / Landmark / Company / School | M42: Does not apply | O42: No
A43: 2024 | B43: January | C43: No | D43: DNA | E43: DNA | F43: Cyber Army of Russia Reborn infiltrates wastewater facility Poland, village of Wydminy | G43: Poland | H43: Sabotage (attempt) | I43: Does not apply | J43: Compromise public utilities | K43: Disrupt daily life | L43: Public services | M43: Does not apply | O43: No
A44: 2024 | B44: January | C44: Yes | D44: 45292 | E44: 45657 | F44: Portal Kombat / Pravda network: websites disseminating pro-Russian content on war in Ukraine to Western audiences (ongoing) | G44: France; Germany; Austria; Switzerland; Poland; Spain; United Kingdom; United States | H44: Influence operation | I44: Does not apply | J44: Compromise domestic / EU politics | K44: Does not apply | L44: Internet / Social media / News | M44: Does not apply | O44: No
A45: 2024 | B45: January | C45: Yes | D45: 45292 | E45: 45443 | F45: Polish authorities arrest Polish, Ukrainian & Belarusian citizens suspected of arson (attempts) in Gdansk, Gdynia & Marki. | G45: Poland | H45: Arson | I45: Does not apply | J45: Disrupt daily life | K45: Inflict economic damage | L45: Public space: Shopping centre / Memorial / Landmark / Company / School | M45: Does not apply | O45: No | P45: See also: https://easternfrontier.eu/eastern-frontier/7,193611,31782457,russian-spy-and-saboteur-set-fire-to-a-hardware-store-in-warsaw.html?disableRedirects=true
A46: 2024 | B46: January | C46: Yes | D46: 45292 | E46: 45657 | F46: Operation Doppelganger: Russian influence campaign that used faked websites (e.g., Der Spiegel, WaPo) to undermine Western support for Ukraine. Social Design Agency. Part of 'Comprehensive Counter Campaign' | G46: Germany; France; United Kingdom; Italy; United States; Ukraine; Latvia; Poland; The Netherlands | H46: Influence operation | I46: Does not apply | J46: Compromise domestic / EU politics | K46: Does not apply | L46: Internet / Social media / News | M46: Does not apply | O46: No | P46: See also: https://mpf.se/psychological-defence-agency/publications/archive/2025-05-15-beyond-operation-doppelganger-a-capability-assessment-of-the-social-design-agency
A47: 2024 | B47: January | C47: Yes | D47: 45292 | E47: 45657 | F47: Ongoing attempt to map offshore comms/energy infrastructure in North Sea / Baltic | G47: North Sea; Baltic Sea | H47: Reconnaissance | I47: Does not apply | J47: Preparation for potential sabotage | K47: Does not apply | L47: Energy / communications infrastructure | M47: Does not apply | O47: No | P47: Ongoing for years.
A48: 2024 | B48: January | C48: Yes | D48: 45292 | E48: 45657 | F48: Monthly 'Peace demonstations' on the Dam in Amsterdam. Monthly since approximately the Russian invasion of Ukraine in 2022. Organized by Dutch peace activists, but supported & financed by Russian organizations. | G48: The Netherlands | H48: Influence operation | I48: Does not apply | J48: Disrupt (military) aid to Ukraine | K48: Does not apply | L48: Public space: Shopping centre / Memorial / Landmark / Company / School | M48: Does not apply | N48: No | O48: No | P48: Appear to have begun in 2023 and to be ongoing in 2025. See: https://kyivindependent.com/who-is-behind-pro-russian-stop-zelensky-demonstrations-in-europe/
A49: 2024 | B49: January | C49: Yes | D49: 45292 | E49: 45534 | F49: Children of war campaign (Kinder des Krieges). Kremlin-backed and AFD supported campaign to sway public opinion against supporting Ukraine. Could not find media articles of exhibits past August 24. | G49: Germany | H49: Influence operation | I49: Does not apply | J49: Disrupt (military) aid to Ukraine | K49: Does not apply | L49: Public space: Shopping centre / Memorial / Landmark / Company / School | M49: Does not apply | N49: No | O49: No | P49: Last (dis)info on this campaign holding exhibits appears to be: https://projekt-kriegskinder.de/
A50: 2024 | B50: January | C50: Yes | D50: 45292 | E50: 45657 | F50: GPS jamming & spoofing over Baltic Sea. As well as near Black Sea. Appears to be permanent. | G50: Baltic Sea; Finland; Latvia; Lithuania; Poland; Romania; Bulgaria | H50: Disruption | I50: Does not apply | J50: Disrupt (civil) aviation | K50: Does not apply | L50: Civil aviation | M50: Does not apply | O50: No
A51: 2024 | B51: January | C51: No | D51: DNA | E51: DNA | F51: Descecration of Alfons Rebane memorial plaque in Mustla | G51: Estonia | H51: Vandalism | I51: Does not apply | J51: Disrupt daily life | K51: Does not apply | L51: Memorial sites / Landmarks | M51: Does not apply | N51: Yes | O51: No
A52: 2024 | B52: January | C52: Yes | D52: 45292 | E52: 45382 | F52: Voice of Europe, cash payments to anti-establishment politicians, Russian attempt to influence EU Parliament elections. Shut down in March 2024. | G52: Germany;Belgium;France;Czechia;Netherlands; | H52: Influence operation | I52: Does not apply | J52: Compromise domestic / EU politics | K52: Disrupt (military) aid to Ukraine | L52: Politician(s) | M52: Does not apply | O52: No | P52: See Wiki for details on period of operation: https://en.wikipedia.org/wiki/Voice_of_Europe#:~:text=The%20organization%20allegedly%20funneled%20up,candidates%20in%20European%20Parliament%20elections.
A53: 2024 | B53: February | C53: No | D53: DNA | E53: DNA | F53: Russians kill defected pilot in Spain | G53: Spain | H53: Assassination | I53: Does not apply | J53: Dissuade defection | K53: Does not apply | L53: Defector(s) | M53: Does not apply | O53: No
A54: 2024 | B54: February | C54: No | D54: DNA | E54: DNA | F54: Arson attempt Latvian Museum of Occupation | G54: Latvia | H54: Arson | I54: Does not apply | J54: Disrupt daily life | K54: Does not apply | L54: Public space: Shopping centre / Memorial / Landmark / Company / School | M54: Does not apply | O54: No
A55: 2024 | B55: February | C55: Yes | D55: 45323 | E55: 45657 | F55: Polish citizen Wiktor Z. (28) detained in June 2025. Suspected of passing information on 'infrastructure critical to Poland's defense' to the Russians from February 2024 onwards. | G55: Poland | H55: Reconnaissance | I55: Does not apply | J55: Preparation for potential sabotage | K55: Does not apply | L55: Military / weapons production infrastructure | M55: Does not apply | N55: Yes | O55: No
A56: 2024 | B56: March | C56: No | D56: DNA | E56: DNA | F56: Arson attack on Ukraine-linked business in East London | G56: United Kingdom | H56: Arson | I56: Does not apply | J56: Disrupt (military) aid to Ukraine | K56: Does not apply | L56: Transport infrastructure | M56: Does not apply | O56: No
A57: 2024 | B57: March | C57: No | D57: DNA | E57: DNA | F57: Arson attack on Ukraine-linked business in Fuenlabrada, outskirts Madrid, linked to London attack | G57: Spain | H57: Arson | I57: Does not apply | J57: Disrupt (military) aid to Ukraine | K57: Does not apply | L57: Transport infrastructure | M57: Does not apply | O57: No | P57: No official allegations of Russian involvement, but included because it fits pattern with earlier arson attack against premises of the same Ukrainian business in London
A58: 2024 | B58: March | C58: No | D58: DNA | E58: DNA | F58: Cyber Army of Russia Reborn infiltrates water mill in France / hydroelectric dam Sur Yvonne | G58: France | H58: Sabotage (attempt) | I58: Does not apply | J58: Compromise public utilities | K58: Disrupt daily life | L58: Public services | M58: Does not apply | O58: No
A59: 2024 | B59: March | C59: No | D59: DNA | E59: DNA | F59: Holocaust memorial in Paris vandalized with paint, pro-Palestinian red hands painted on memorial, police suspect Russia | G59: France | H59: Vandalism | I59: Does not apply | J59: Disrupt daily life | K59: Does not apply | L59: Public space: Shopping centre / Memorial / Landmark / Company / School | M59: Does not apply | O59: No
A60: 2024 | B60: March | C60: No | D60: DNA | E60: DNA | F60: Multiple 'caution, balcony can collapse' sprayed on Paris balconies, playing on fear of such an incident during Olympics | G60: France | H60: Vandalism | I60: Does not apply | J60: Disrupt daily life | K60: Does not apply | L60: Public space: Shopping centre / Memorial / Landmark / Company / School | M60: Does not apply | O60: No
A61: 2024 | B61: March | C61: No | D61: DNA | E61: DNA | F61: France blocks fake enlistment website for war in Ukraine, intended to fan fear of France joining the conflict | G61: France | H61: Influence operation | I61: Does not apply | J61: Compromise domestic / EU politics | K61: Does not apply | L61: Internet / Social media / News | M61: Does not apply | O61: No
A62: 2024 | B62: March | C62: Yes | D62: March | E62: July | F62: Thwarted plot to kill Rheinmetall CEO Armin Papperger. Thwarted at the latest July 2024, when news broke in the media. Plot dated to 'earlier this year' according to CNN. Earlier this year may have been March, see extra info | G62: Germany | H62: Assassination (plot) | I62: Does not apply | J62: Disrupt (military) aid to Ukraine | K62: Does not apply | L62: Industrialist(s) | M62: Does not apply | O62: No | P62: https://www.pravda.com.ua/eng/news/2025/02/07/7497221/
A63: 2024 | B63: April | C63: No | D63: DNA | E63: DNA | F63: Two Russian spies arrested for spionage US bases & planning sabotage military transport routes | G63: Germany | H63: Sabotage (preparation) | I63: Does not apply | J63: Disrupt (military) aid to Ukraine | K63: Does not apply | L63: Arms deliveries to Ukraine | M63: Military / weapons production infrastructure | O63: No
A64: 2024 | B64: April | C64: No | D64: DNA | E64: DNA | F64: Pole Pawel K. arrested for involvement in plot to assassinate Zelensky. | G64: Poland | H64: Assassination (plot) | I64: Does not apply | J64: Kill politician / head of state | K64: Does not apply | L64: Politician(s) | M64: Does not apply | O64: No
A65: 2024 | B65: April | C65: No | D65: DNA | E65: DNA | F65: Russian embassy in Spain places video on X / Twitter purporting to show Spanish troops in Ukraine | G65: Spain | H65: Influence operation | I65: Does not apply | J65: Compromise domestic / EU politics | K65: Does not apply | L65: Internet / Social media / News | M65: Does not apply | O65: No
A66: 2024 | B66: April | C66: No | D66: DNA | E66: DNA | F66: Belarusian Stepan K. set fire to large department / DIY store in Warsaw, April 2024. Store belonged to OBI, German home improvement store. Separate from May 2024 Warsaw fire. | G66: Poland | H66: Arson | I66: Does not apply | J66: Disrupt daily life | K66: Inflict economic damage | L66: Public space: Shopping centre / Memorial / Landmark / Company / School | M66: Does not apply | O66: No
A67: 2024 | B67: April | C67: No | D67: DNA | E67: DNA | F67: 1000 stickers calling for an end to the war in Ukraine placed across Paris | G67: France | H67: Influence operation | I67: Does not apply | J67: Compromise domestic / EU politics | K67: Does not apply | L67: Public space: Shopping centre / Memorial / Landmark / Company / School | M67: Does not apply | N67: Yes | O67: No | P67: Only mentioned in in-depth journalistic reporting on the 'red hands' case. See link
A68: 2024 | B68: May | C68: No | D68: DNA | E68: DNA | F68: Shopping mall fire in Warsaw, Poland | G68: Poland | H68: Arson | I68: Does not apply | J68: Disrupt daily life | K68: Inflict economic damage | L68: Public space: Shopping centre / Memorial / Landmark / Company / School | M68: Does not apply | O68: No | P68: March 2025: extra confirmation.
A69: 2024 | B69: May | C69: No | D69: DNA | E69: DNA | F69: Arson attack IKEA Vilnius | G69: Lithuania | H69: Arson | I69: Does not apply | J69: Disrupt daily life | K69: Inflict economic damage | L69: Public space: Shopping centre / Memorial / Landmark / Company / School | M69: Does not apply | O69: No | P69: March 2025: extra confirmation.
A70: 2024 | B70: May | C70: No | D70: DNA | E70: DNA | F70: Russia removes border buoys Estonian river Narva | G70: Estonia | H70: Vandalism | I70: Does not apply | J70: Disrupt daily life | K70: Does not apply | L70: Border | M70: Does not apply | O70: No
A71: 2024 | B71: May | C71: No | D71: DNA | E71: DNA | F71: 1.000+ fake bomb threats emailed to schools, banks in Slovakia | G71: Slovakia | H71: Terrorism | I71: Does not apply | J71: Disrupt daily life | K71: Does not apply | L71: Public space: Shopping centre / Memorial / Landmark / Company / School | M71: Does not apply | O71: No | P71: For now, schools made part of 'public space' category to avoid too-finegrained disaggregation.
A72: 2024 | B72: May | C72: No | D72: DNA | E72: DNA | F72: Fake news report on Poland mobilizing 200.000 men placed on polish national news agency - hack by Russians | G72: Poland | H72: Influence operation | I72: Does not apply | J72: Compromise domestic / EU politics | K72: Does not apply | L72: Internet / Social media / News | M72: Does not apply | O72: No
A73: 2024 | B73: May | C73: No | D73: DNA | E73: DNA | F73: Defacing the tombstone of Ukrainian politician Stepan Bandera in Munich | G73: Germany | H73: Vandalism | I73: Does not apply | J73: Compromise domestic / EU politics | K73: Does not apply | L73: Public space: Shopping centre / Memorial / Landmark / Company / School | M73: Does not apply | N73: Yes | O73: No | P73: See also: https://www.ukrainianworldcongress.org/russian-disinformation-in-action-banderas-grave-vandalized-with-provocative-writing/
A74: 2024 | B74: May | C74: No | D74: DNA | E74: DNA | F74: Arson attempt construction warehouse / supply depot Warsaw 1/2 | G74: Poland | H74: Arson | I74: Does not apply | J74: Disrupt daily life | K74: Does not apply | L74: Public space: Shopping centre / Memorial / Landmark / Company / School | M74: Does not apply | N74: Yes | O74: No | P74: Conducted by Colombian national de la Cruz
A75: 2024 | B75: May | C75: No | D75: DNA | E75: DNA | F75: Arson attempt construction warehouse / supply depot Radom 2/2 | G75: Poland | H75: Arson | I75: Does not apply | J75: Disrupt daily life | K75: Does not apply | L75: Public space: Shopping centre / Memorial / Landmark / Company / School | M75: Does not apply | N75: Yes | O75: No | P75: Conducted by Colombian national de la Cruz
A76: 2024 | B76: June | C76: No | D76: DNA | E76: DNA | F76: Arson attempt on buses in Prague | G76: Czechia | H76: Arson | I76: Does not apply | J76: Disrupt daily life | K76: Does not apply | L76: Transport infrastructure | M76: Does not apply | O76: No
A77: 2024 | B77: June | C77: No | D77: DNA | E77: DNA | F77: Five coffins with French flag & 'French soldiers in Ukraine' near Eiffel tower | G77: France | H77: Influence operation | I77: Does not apply | J77: Disrupt (military) aid to Ukraine | K77: Does not apply | L77: Public space: Shopping centre / Memorial / Landmark / Company / School | M77: Does not apply | O77: No
A78: 2024 | B78: June | C78: No | D78: DNA | E78: DNA | F78: Russian-Ukrainian man arrested in Paris with explosives, intended to target hardware store | G78: France | H78: Sabotage (preparation) | I78: Does not apply | J78: Inflict economic damage | K78: Disrupt daily life | L78: Public space: Shopping centre / Memorial / Landmark / Company / School | M78: Does not apply | O78: No
A79: 2024 | B79: June | C79: Yes | D79: June | E79: July | F79: 11 break-ins in Finish water towers / treatment plants | G79: Finland | H79: Reconnaissance | I79: Does not apply | J79: Preparation for potential sabotage | K79: Does not apply | L79: Public services | M79: Does not apply | O79: No | P79: Border-line case due to lack of authorities claiming probable Russian involvement. Included because it fits pattern of intrusions into water facilities in Sweden, Germany, Poland, France.
A80: 2024 | B80: June | C80: Yes | D80: June | E80: July | F80: Russia-linked network active on X / Twitter 'around time of European elections' promoted French & German radical-right parties. Also active in Italy. Trollrensics report. | G80: Germany; France; Italy | H80: Influence operation | I80: Does not apply | J80: Compromise domestic / EU politics | K80: Does not apply | L80: Internet / Social media / News | M80: Does not apply | O80: No
A81: 2024 | B81: June | C81: No | D81: DNA | E81: DNA | F81: Russian hacktivists tried to make voting for EU parliament difficult for Dutch citizens through DDoS attack against political parties' websites and public transportation companies in NL. Appears unsuccesful | G81: The Netherlands | H81: Sabotage (attempt) | I81: Does not apply | J81: Compromise domestic / EU politics | K81: Does not apply | L81: Internet / Social media / News | M81: Public services | O81: Yes | P81: Is public transport the same as public service, or should it be its own category?
A82: 2024 | B82: June | C82: No | D82: DNA | E82: DNA | F82: Placing stickers near hotels in Zurich, ahead of a peace conference on Ukraine | G82: Switzerland | H82: Influence operation | I82: Does not apply | J82: Compromise domestic / EU politics | K82: Does not apply | L82: Public space: Shopping centre / Memorial / Landmark / Company / School | M82: Does not apply | N82: Yes | O82: No
A83: 2024 | B83: June | C83: No | D83: DNA | E83: DNA | F83: Coffin graffiti / stencils appear in Paris. Likely linked to actual coffins placed near Eiffel tower | G83: France | H83: Influence operation | I83: Does not apply | J83: Compromise domestic / EU politics | K83: Does not apply | L83: Public space: Shopping centre / Memorial / Landmark / Company / School | M83: Does not apply | N83: Yes | O83: No | P83: See also: https://www.rferl.org/a/ukraine-russia-paris-coffin-graffiti-moldova/32984608.html
A84: 2024 | B84: July | C84: No | D84: DNA | E84: DNA | F84: Incendiary device placed on plane, ignites in DHL warehouse UK | G84: United Kingdom | H84: Sabotage | I84: Terrorism | J84: Disrupt daily life | K84: Inflict economic damage | L84: Civil aviation | M84: Transport infrastructure | O84: No | P84: More details: https://www.tagesschau.de/investigativ/ndr-wdr/russland-sabotage-106.html?at_medium=tagesschau&at_campaign=DeviceSharing&at_content=SiteSharing
A85: 2024 | B85: July | C85: No | D85: DNA | E85: DNA | F85: Incendiary device about to be loaded on plane, ignites in DHL warehouse Germany | G85: Germany | H85: Sabotage | I85: Terrorism | J85: Disrupt daily life | K85: Inflict economic damage | L85: Civil aviation | M85: Transport infrastructure | O85: No
A86: 2024 | B86: July | C86: No | D86: DNA | E86: DNA | F86: Russian arrested on suspicion of plot to destabilize Olympics | G86: France | H86: Unknown | I86: Does not apply | J86: Disrupt daily life | K86: Does not apply | L86: Public space: Shopping centre / Memorial / Landmark / Company / School | M86: Does not apply | O86: No
A87: 2024 | B87: July | C87: No | D87: DNA | E87: DNA | F87: Explosive / inflammable parcel ignites in courier truck / storage site near Warsaw. Linked to perpetrators of DHL attacks | G87: Poland | H87: Sabotage | I87: Does not apply | J87: Inflict economic damage | K87: Does not apply | L87: Transport infrastructure | M87: Does not apply | O87: No | P87: Sabotage not terrorism, as unclear whether this was intended to go on a plane or not.
A88: 2024 | B88: July | C88: No | D88: DNA | E88: DNA | F88: Colombian national engaged in sabotage preparations in Romania, targets appear to be economic / infrastructure related | G88: Romania | H88: Sabotage (preparation) | I88: Does not apply | J88: Degrade energy supply / communications infrastructure | K88: Inflict economic damage | L88: Energy / communications infrastructure | M88: Does not apply | O88: No
A89: 2024 | B89: July | C89: No | D89: DNA | E89: DNA | F89: Parcel bomb plot, Poland, July 2024 | G89: Poland | H89: Terrorism | I89: Does not apply | J89: Unknown | K89: Does not apply | L89: Unknown | M89: Does not apply | N89: Yes | O89: No | P89: Addressee of the parcel containing the bomb not disclosed, hence unable to ascertain goal & target type. See also: https://www.gov.pl/web/prokuratura-krajowa/akt-oskarzenia-o-wspoludzial-w-sprowadzeniu-bezposredniego-niebezpieczenstwa-eksplozji-materialow-wybuchowych2?
A90: 2024 | B90: July | C90: No | D90: DNA | E90: DNA | F90: Arson in Leroy Merlin DIY / home improvement store in Lodz, Poland. Perpetrator linked to 2024 DHL plot | G90: Poland | H90: Arson | I90: Does not apply | J90: Disrupt daily life | K90: Inflict economic damage | L90: Public space: Shopping centre / Memorial / Landmark / Company / School | M90: Does not apply | N90: Yes | O90: No | P90: Revealed in September 2025 Vsquare reporting on 2024 DHL plot.
A91: 2024 | B91: July | C91: No | D91: DNA | E91: DNA | F91: Wladyslaw D. tasked by GRU to dig up cans w. explosives, drone parts, in Lithuanian cemetery, leaving items in Poland, Germany. Intent unclear, but seems likely sabotage (or terrorism) prep. | G91: Poland; Lithuania; Germany | H91: Unknown | I91: Does not apply | J91: Unknown | K91: Does not apply | L91: Unknown | M91: Does not apply | N91: Yes | O91: No
A92: 2024 | B92: August | C92: No | D92: DNA | E92: DNA | F92: Hole cut in fence around water treatment plant near Cologne | G92: Germany | H92: Reconnaissance | I92: Does not apply | J92: Preparation for potential sabotage | K92: Disrupt daily life | L92: Public services | M92: Does not apply | O92: No
A93: 2024 | B93: August | C93: No | D93: DNA | E93: DNA | F93: Planned / attempted sabotage attack against Geilenkirchen base with drones | G93: Germany | H93: Reconnaissance | I93: Does not apply | J93: Preparation for potential sabotage | K93: Does not apply | L93: Military / weapons production infrastructure | M93: Does not apply | O93: No
A94: 2024 | B94: August | C94: No | D94: DNA | E94: DNA | F94: Ukrainian man in Amsterdam unwittingly recruited via Telegram to send package via DHL, appears to be part of test-run for attacks using airlines. Linked to other DHL attacks. | G94: The Netherlands | H94: Sabotage (preparation) | I94: Does not apply | J94: Disrupt daily life | K94: Inflict economic damage | L94: Civil aviation | M94: Does not apply | N94: Yes | O94: No | P94: A -so far- rare case of agents who appear to have been unwittingly used for Russia hybrid ops.
A95: 2024 | B95: August | C95: No | D95: DNA | E95: DNA | F95: Digital and/or physical break-ins Swedish arms manufacturers, potential sabotage prep / disruption | G95: Sweden | H95: Sabotage (preparation) | I95: Does not apply | J95: Disrupt (military) aid to Ukraine | K95: Does not apply | L95: Military / weapons production infrastructure | M95: Does not apply | O95: No
A96: 2024 | B96: September | C96: No | D96: DNA | E96: DNA | F96: Hundreds of schools forced to close due to fake bomb threats per email. Head Czech secret service blames Russia | G96: Czechia | H96: Terrorism | I96: Does not apply | J96: Disrupt daily life | K96: Does not apply | L96: Public space: Shopping centre / Memorial / Landmark / Company / School | M96: Does not apply | O96: No
A97: 2024 | B97: September | C97: No | D97: DNA | E97: DNA | F97: Two Spanish nationals traveled to Lithuania in September to set fire to TVC Solutions, company in Siauliai. One is also Russian national. Failed, fled to Latvia. | G97: Lithuania | H97: Arson | I97: Does not apply | J97: Disrupt daily life | K97: Does not apply | L97: Public space: Shopping centre / Memorial / Landmark / Company / School | M97: Does not apply | O97: Yes
A98: 2024 | B98: October | C98: No | D98: DNA | E98: DNA | F98: Intrusion into Swedish water treatment plant | G98: Sweden | H98: Reconnaissance | I98: Does not apply | J98: Preparation for potential sabotage | K98: Disrupt daily life | L98: Public services | M98: Does not apply | O98: No
A99: 2024 | B99: November | C99: No | D99: DNA | E99: DNA | F99: Russian GPS jamming of Finish airports | G99: Finland | H99: Disruption | I99: Does not apply | J99: Disrupt (civil) aviation | K99: Does not apply | L99: Civil aviation | M99: Does not apply | O99: No
A100: 2024 | B100: November | C100: No | D100: DNA | E100: DNA | F100: Undersea cables between Finland & Germany, Sweden & Latvia cut, sabotage probable / Yi Peng 3 incident | G100: Baltic Sea | H100: Sabotage | I100: Does not apply | J100: Degrade energy supply / communications infrastructure | K100: Does not apply | L100: Energy / communications infrastructure | M100: Does not apply | O100: No | P100: Chinese ship appears to have carried out sabotage on behest of / under pressure by Russian authorities
...

Sheet Visualization
A1: Year | B1: No. Of incidents | C1: Excluded incidents | D1: Excluded Ratio | F1: MonthStart | G1: Multi-month operations | H1: Single-month operations | I1: TotalOpsPerMonth | K1: Type of incident | L1: 2022 | M1: 2023 | N1: 2024 | O1: 2025 | P1: Totals | R1: Apparent Goal | S1: 2022 | T1: 2023 | U1: 2024 | V1: 2025 | W1: Totals | Y1: Type of target | Z1: 2022 | AA1: 2023 | AB1: 2024 | AC1: 2025 | AD1: Totals | AF1: Locations targeted | AG1: 2022 | AH1: 2023 | AI1: 2024 | AJ1: 2025 | AK1: Totals
A2: 2022 | B2: =COUNTIF(EventData!A:A, "2022") -> 13 | C2: =COUNTIF(Excluded!A:A,"2022") -> 11 | D2: =C2/(SUM(B2:C2)) -> 0.45833333 | F2: 44562 | G2: =COUNTIFS(EventData!D:D,"<=" & EOMONTH(F2,0),EventData!E:E,">=" & F2) -> 1 | H2: =COUNTIFS(EventData!A:A,YEAR(F2),EventData!B:B,TEXT(F2,"mmmm"),EventData!C:C,"NO") -> 0 | I2: =SUM(G2:H2) -> 1 | K2: Assassination** | L2: =COUNTIFS(EventData!A:A,"2022",EventData!H:H,"*assassination*")+COUNTIFS(EventData!A:A,"2022",EventData!I:I,"*assassination*") -> 0 | M2: =COUNTIFS(EventData!A:A,"2023",EventData!H:H,"*assassination*")+COUNTIFS(EventData!A:A,"2023",EventData!I:I,"*assassination*") -> 0 | N2: =COUNTIFS(EventData!A:A,"2024",EventData!H:H,"*assassination*")+COUNTIFS(EventData!A:A,"2024",EventData!I:I,"*assassination*") -> 3 | O2: =COUNTIFS(EventData!A:A,"2025",EventData!H:H,"*assassination*")+COUNTIFS(EventData!A:A,"2025",EventData!I:I,"*assassination*") -> 0 | P2: =SUM(L2:O2) -> 3 | R2: Dissuade defection | S2: =COUNTIFS(EventData!A:A,"2022",EventData!J:J,"Dissuade defection")+COUNTIFS(EventData!A:A,"2022",EventData!K:K,"Dissuade defection") -> 0 | T2: =COUNTIFS(EventData!A:A,"2023",EventData!J:J,"Dissuade defection")+COUNTIFS(EventData!A:A,"2023",EventData!K:K,"Dissuade defection") -> 0 | U2: =COUNTIFS(EventData!A:A,"2024",EventData!J:J,"Dissuade defection")+COUNTIFS(EventData!A:A,"2024",EventData!K:K,"Dissuade defection") -> 1 | V2: =COUNTIFS(EventData!A:A,"2025",EventData!J:J,"Dissuade defection")+COUNTIFS(EventData!A:A,"2025",EventData!K:K,"Dissuade defection") -> 0 | W2: =SUM(S2:V2) -> 1 | Y2: Industrialist(s) | Z2: =COUNTIFS(EventData!A:A,"2022",EventData!L:L,"industrialist(s)")+COUNTIFS(EventData!A:A,"2022",EventData!M:M,"industrialist(s)") -> 0 | AA2: =COUNTIFS(EventData!A:A,"2023",EventData!L:L,"industrialist(s)")+COUNTIFS(EventData!A:A,"2023",EventData!M:M,"industrialist(s)") -> 0 | AB2: =COUNTIFS(EventData!A:A,"2024",EventData!L:L,"industrialist(s)")+COUNTIFS(EventData!A:A,"2024",EventData!M:M,"industrialist(s)") -> 1 | AC2: =COUNTIFS(EventData!A:A,"2025",EventData!L:L,"industrialist(s)")+COUNTIFS(EventData!A:A,"2025",EventData!M:M,"industrialist(s)") -> 0 | AD2: =SUM(Z2:AC2) -> 1 | AF2: Germany | AG2: =COUNTIFS(EventData!A:A,"2022",EventData!G:G,"*germany*") -> 6 | AH2: =COUNTIFS(EventData!A:A,"2023",EventData!G:G,"*germany*") -> 6 | AI2: =COUNTIFS(EventData!A:A,"2024",EventData!G:G,"*germany*") -> 14 | AJ2: =COUNTIFS(EventData!A:A,"2025",EventData!G:G,"*germany*") -> 10 | AK2: =SUM(AG2:AJ2) -> 36
A3: 2023 | B3: =COUNTIF(EventData!A:A, "2023") -> 24 | C3: =COUNTIF(Excluded!A:A,"2023") -> 3 | D3: =C3/(SUM(B3:C3)) -> 0.11111111 | F3: 44593 | G3: =COUNTIFS(EventData!D:D,"<=" & EOMONTH(F3,0),EventData!E:E,">=" & F3) -> 1 | H3: =COUNTIFS(EventData!A:A,YEAR(F3),EventData!B:B,TEXT(F3,"mmmm"),EventData!C:C,"NO") -> 0 | I3: =SUM(G3:H3) -> 1 | K3: Unknown | L3: =COUNTIFS(EventData!A:A,"2022",EventData!H:H,"*unknown*")+COUNTIFS(EventData!A:A,"2022",EventData!I:I,"*unknown*") -> 0 | M3: =COUNTIFS(EventData!A:A,"2023",EventData!H:H,"*unknown*")+COUNTIFS(EventData!A:A,"2023",EventData!I:I,"*unknown*") -> 0 | N3: =COUNTIFS(EventData!A:A,"2024",EventData!H:H,"*unknown*")+COUNTIFS(EventData!A:A,"2024",EventData!I:I,"*unknown*") -> 2 | O3: =COUNTIFS(EventData!A:A,"2025",EventData!H:H,"*unknown*")+COUNTIFS(EventData!A:A,"2025",EventData!I:I,"*unknown*") -> 2 | P3: =SUM(L3:O3) -> 4 | R3: Kill politician / head of state | S3: =COUNTIFS(EventData!A:A,"2022",EventData!J:J,"Kill politician*")+COUNTIFS(EventData!A:A,"2022",EventData!K:K,"Kill politician*") -> 0 | T3: =COUNTIFS(EventData!A:A,"2023",EventData!J:J,"Kill politician*")+COUNTIFS(EventData!A:A,"2023",EventData!K:K,"Kill politician*") -> 0 | U3: =COUNTIFS(EventData!A:A,"2024",EventData!J:J,"Kill politician*")+COUNTIFS(EventData!A:A,"2024",EventData!K:K,"Kill politician*") -> 1 | V3: =COUNTIFS(EventData!A:A,"2025",EventData!J:J,"Kill politician*")+COUNTIFS(EventData!A:A,"2025",EventData!K:K,"Kill politician*") -> 0 | W3: =SUM(S3:V3) -> 1 | Y3: Defector(s) | Z3: =COUNTIFS(EventData!A:A,"2022",EventData!L:L,"defector(s)")+COUNTIFS(EventData!A:A,"2022",EventData!M:M,"defector(s)") -> 0 | AA3: =COUNTIFS(EventData!A:A,"2023",EventData!L:L,"defector(s)")+COUNTIFS(EventData!A:A,"2023",EventData!M:M,"defector(s)") -> 0 | AB3: =COUNTIFS(EventData!A:A,"2024",EventData!L:L,"defector(s)")+COUNTIFS(EventData!A:A,"2024",EventData!M:M,"defector(s)") -> 1 | AC3: =COUNTIFS(EventData!A:A,"2025",EventData!L:L,"defector(s)")+COUNTIFS(EventData!A:A,"2025",EventData!M:M,"defector(s)") -> 0 | AD3: =SUM(Z3:AC3) -> 1 | AF3: Poland | AG3: =COUNTIFS(EventData!A:A,"2022",EventData!G:G,"*poland*") -> 1 | AH3: =COUNTIFS(EventData!A:A,"2023",EventData!G:G,"*poland*") -> 4 | AI3: =COUNTIFS(EventData!A:A,"2024",EventData!G:G,"*poland*") -> 17 | AJ3: =COUNTIFS(EventData!A:A,"2025",EventData!G:G,"*poland*") -> 8 | AK3: =SUM(AG3:AJ3) -> 30
A4: 2024 | B4: =COUNTIF(EventData!A:A, "2024") -> 69 | C4: =COUNTIF(Excluded!A:A,"2024") -> 25 | D4: =C4/(SUM(B4:C4)) -> 0.26595745 | F4: 44621 | G4: =COUNTIFS(EventData!D:D,"<=" & EOMONTH(F4,0),EventData!E:E,">=" & F4) -> 2 | H4: =COUNTIFS(EventData!A:A,YEAR(F4),EventData!B:B,TEXT(F4,"mmmm"),EventData!C:C,"NO") -> 0 | I4: =SUM(G4:H4) -> 2 | K4: Disruptive immigration | L4: =COUNTIFS(EventData!A:A,"2022",EventData!H:H,"*immigration*")+COUNTIFS(EventData!A:A,"2022",EventData!I:I,"*immigration*") -> 0 | M4: =COUNTIFS(EventData!A:A,"2023",EventData!H:H,"*immigration*")+COUNTIFS(EventData!A:A,"2023",EventData!I:I,"*immigration*") -> 3 | N4: =COUNTIFS(EventData!A:A,"2024",EventData!H:H,"*immigration*")+COUNTIFS(EventData!A:A,"2024",EventData!I:I,"*immigration*") -> 1 | O4: =COUNTIFS(EventData!A:A,"2025",EventData!H:H,"*immigration*")+COUNTIFS(EventData!A:A,"2025",EventData!I:I,"*immigration*") -> 1 | P4: =SUM(L4:O4) -> 5 | R4: Degrade military infrastructure | S4: =COUNTIFS(EventData!A:A,"2022",EventData!J:J,"Degrade military infrastructure")+COUNTIFS(EventData!A:A,"2022",EventData!K:K,"Degrade military infrastructure") -> 0 | T4: =COUNTIFS(EventData!A:A,"2023",EventData!J:J,"Degrade military infrastructure")+COUNTIFS(EventData!A:A,"2023",EventData!K:K,"Degrade military infrastructure") -> 1 | U4: =COUNTIFS(EventData!A:A,"2024",EventData!J:J,"Degrade military infrastructure")+COUNTIFS(EventData!A:A,"2024",EventData!K:K,"Degrade military infrastructure") -> 0 | V4: =COUNTIFS(EventData!A:A,"2025",EventData!J:J,"Degrade military infrastructure")+COUNTIFS(EventData!A:A,"2025",EventData!K:K,"Degrade military infrastructure") -> 1 | W4: =SUM(S4:V4) -> 2 | Y4: Journalist(s) | Z4: =COUNTIFS(EventData!A:A,"2022",EventData!L:L,"journalist(s)")+COUNTIFS(EventData!A:A,"2022",EventData!M:M,"journalist(s)") -> 0 | AA4: =COUNTIFS(EventData!A:A,"2023",EventData!L:L,"journalist(s)")+COUNTIFS(EventData!A:A,"2023",EventData!M:M,"journalist(s)") -> 1 | AB4: =COUNTIFS(EventData!A:A,"2024",EventData!L:L,"journalist(s)")+COUNTIFS(EventData!A:A,"2024",EventData!M:M,"journalist(s)") -> 0 | AC4: =COUNTIFS(EventData!A:A,"2025",EventData!L:L,"journalist(s)")+COUNTIFS(EventData!A:A,"2025",EventData!M:M,"journalist(s)") -> 0 | AD4: =SUM(Z4:AC4) -> 1 | AF4: France | AG4: =COUNTIFS(EventData!A:A,"2022",EventData!G:G,"*france*") -> 2 | AH4: =COUNTIFS(EventData!A:A,"2023",EventData!G:G,"*france*") -> 7 | AI4: =COUNTIFS(EventData!A:A,"2024",EventData!G:G,"*france*") -> 14 | AJ4: =COUNTIFS(EventData!A:A,"2025",EventData!G:G,"*france*") -> 6 | AK4: =SUM(AG4:AJ4) -> 29
A5: 2025 | B5: =COUNTIF(EventData!A:A, "2025") -> 40 | C5: =COUNTIF(Excluded!A:A,"2025") -> 39 | D5: =C5/(SUM(B5:C5)) -> 0.49367089 | F5: 44652 | G5: =COUNTIFS(EventData!D:D,"<=" & EOMONTH(F5,0),EventData!E:E,">=" & F5) -> 2 | H5: =COUNTIFS(EventData!A:A,YEAR(F5),EventData!B:B,TEXT(F5,"mmmm"),EventData!C:C,"NO") -> 2 | I5: =SUM(G5:H5) -> 4 | K5: Terrorism* | L5: =COUNTIFS(EventData!A:A,"2022",EventData!H:H,"*terrorism*")+COUNTIFS(EventData!A:A,"2022",EventData!I:I,"*terrorism*") -> 1 | M5: =COUNTIFS(EventData!A:A,"2023",EventData!H:H,"*terrorism*")+COUNTIFS(EventData!A:A,"2023",EventData!I:I,"*terrorism*") -> 1 | N5: =COUNTIFS(EventData!A:A,"2024",EventData!H:H,"*terrorism*")+COUNTIFS(EventData!A:A,"2024",EventData!I:I,"*terrorism*") -> 5 | O5: =COUNTIFS(EventData!A:A,"2025",EventData!H:H,"*terrorism*")+COUNTIFS(EventData!A:A,"2025",EventData!I:I,"*terrorism*") -> 2 | P5: =SUM(L5:O5) -> 9 | R5: Intimidate politician / journalist | S5: =COUNTIFS(EventData!A:A,"2022",EventData!J:J,"*intimidate*")+COUNTIFS(EventData!A:A,"2022",EventData!K:K,"*intimidate*") -> 0 | T5: =COUNTIFS(EventData!A:A,"2023",EventData!J:J,"*intimidate*")+COUNTIFS(EventData!A:A,"2023",EventData!K:K,"*intimidate*") -> 2 | U5: =COUNTIFS(EventData!A:A,"2024",EventData!J:J,"*intimidate*")+COUNTIFS(EventData!A:A,"2024",EventData!K:K,"*intimidate*") -> 0 | V5: =COUNTIFS(EventData!A:A,"2025",EventData!J:J,"*intimidate*")+COUNTIFS(EventData!A:A,"2025",EventData!K:K,"*intimidate*") -> 1 | W5: =SUM(S5:V5) -> 3 | Y5: Economic infrastructure | Z5: =COUNTIFS(EventData!A:A,"2022",EventData!L:L,"*economic infra*")+COUNTIFS(EventData!A:A,"2022",EventData!M:M,"*economic infra*") -> 0 | AA5: =COUNTIFS(EventData!A:A,"2023",EventData!L:L,"*economic infra*")+COUNTIFS(EventData!A:A,"2023",EventData!M:M,"*economic infra*") -> 0 | AB5: =COUNTIFS(EventData!A:A,"2024",EventData!L:L,"*economic infra*")+COUNTIFS(EventData!A:A,"2024",EventData!M:M,"*economic infra*") -> 0 | AC5: =COUNTIFS(EventData!A:A,"2025",EventData!L:L,"*economic infra*")+COUNTIFS(EventData!A:A,"2025",EventData!M:M,"*economic infra*") -> 1 | AD5: =SUM(Z5:AC5) -> 1 | AF5: The Netherlands | AG5: =COUNTIFS(EventData!A:A,"2022",EventData!G:G,"*netherlands*") -> 1 | AH5: =COUNTIFS(EventData!A:A,"2023",EventData!G:G,"*netherlands*") -> 4 | AI5: =COUNTIFS(EventData!A:A,"2024",EventData!G:G,"*netherlands*") -> 7 | AJ5: =COUNTIFS(EventData!A:A,"2025",EventData!G:G,"*netherlands*") -> 3 | AK5: =SUM(AG5:AJ5) -> 15
A6: Totals | B6: =SUM(B2:B5) -> 146 | C6: =SUM(C2:C5) -> 78 | D6: =C6/(SUM(B6:C6)) -> 0.34821429 | F6: 44682 | G6: =COUNTIFS(EventData!D:D,"<=" & EOMONTH(F6,0),EventData!E:E,">=" & F6) -> 3 | H6: =COUNTIFS(EventData!A:A,YEAR(F6),EventData!B:B,TEXT(F6,"mmmm"),EventData!C:C,"NO") -> 1 | I6: =SUM(G6:H6) -> 4 | K6: Vandalism | L6: =COUNTIFS(EventData!A:A,"2022",EventData!H:H,"*vandalism*")+COUNTIFS(EventData!A:A,"2022",EventData!I:I,"*vandalism*") -> 1 | M6: =COUNTIFS(EventData!A:A,"2023",EventData!H:H,"*vandalism*")+COUNTIFS(EventData!A:A,"2023",EventData!I:I,"*vandalism*") -> 4 | N6: =COUNTIFS(EventData!A:A,"2024",EventData!H:H,"*vandalism*")+COUNTIFS(EventData!A:A,"2024",EventData!I:I,"*vandalism*") -> 6 | O6: =COUNTIFS(EventData!A:A,"2025",EventData!H:H,"*vandalism*")+COUNTIFS(EventData!A:A,"2025",EventData!I:I,"*vandalism*") -> 1 | P6: =SUM(L6:O6) -> 12 | R6: Compromise public utilities | S6: =COUNTIFS(EventData!A:A,"2022",EventData!J:J,"Compromise public utilities")+COUNTIFS(EventData!A:A,"2022",EventData!K:K,"Compromise public utilities") -> 0 | T6: =COUNTIFS(EventData!A:A,"2023",EventData!J:J,"Compromise public utilities")+COUNTIFS(EventData!A:A,"2023",EventData!K:K,"Compromise public utilities") -> 0 | U6: =COUNTIFS(EventData!A:A,"2024",EventData!J:J,"Compromise public utilities")+COUNTIFS(EventData!A:A,"2024",EventData!K:K,"Compromise public utilities") -> 3 | V6: =COUNTIFS(EventData!A:A,"2025",EventData!J:J,"Compromise public utilities")+COUNTIFS(EventData!A:A,"2025",EventData!K:K,"Compromise public utilities") -> 1 | W6: =SUM(S6:V6) -> 4 | Y6: Arms deliveries to Ukraine | Z6: =COUNTIFS(EventData!A:A,"2022",EventData!L:L,"Arms deliveries to Ukraine")+COUNTIFS(EventData!A:A,"2022",EventData!M:M,"Arms deliveries to Ukraine") -> 0 | AA6: =COUNTIFS(EventData!A:A,"2023",EventData!L:L,"Arms deliveries to Ukraine")+COUNTIFS(EventData!A:A,"2023",EventData!M:M,"Arms deliveries to Ukraine") -> 0 | AB6: =COUNTIFS(EventData!A:A,"2024",EventData!L:L,"Arms deliveries to Ukraine")+COUNTIFS(EventData!A:A,"2024",EventData!M:M,"Arms deliveries to Ukraine") -> 1 | AC6: =COUNTIFS(EventData!A:A,"2025",EventData!L:L,"Arms deliveries to Ukraine")+COUNTIFS(EventData!A:A,"2025",EventData!M:M,"Arms deliveries to Ukraine") -> 1 | AD6: =SUM(Z6:AC6) -> 2 | AF6: United Kingdom | AG6: =COUNTIFS(EventData!A:A,"2022",EventData!G:G,"*united kingdom*") -> 2 | AH6: =COUNTIFS(EventData!A:A,"2023",EventData!G:G,"*united kingdom*") -> 2 | AI6: =COUNTIFS(EventData!A:A,"2024",EventData!G:G,"*united kingdom*") -> 4 | AJ6: =COUNTIFS(EventData!A:A,"2025",EventData!G:G,"*united kingdom*") -> 3 | AK6: =SUM(AG6:AJ6) -> 11
F7: 44713 | G7: =COUNTIFS(EventData!D:D,"<=" & EOMONTH(F7,0),EventData!E:E,">=" & F7) -> 4 | H7: =COUNTIFS(EventData!A:A,YEAR(F7),EventData!B:B,TEXT(F7,"mmmm"),EventData!C:C,"NO") -> 0 | I7: =SUM(G7:H7) -> 4 | K7: Disruption | L7: =COUNTIFS(EventData!A:A,"2022",EventData!H:H,"disruption")+COUNTIFS(EventData!A:A,"2022",EventData!I:I,"disruption") -> 1 | M7: =COUNTIFS(EventData!A:A,"2023",EventData!H:H,"disruption")+COUNTIFS(EventData!A:A,"2023",EventData!I:I,"disruption") -> 1 | N7: =COUNTIFS(EventData!A:A,"2024",EventData!H:H,"disruption")+COUNTIFS(EventData!A:A,"2024",EventData!I:I,"disruption") -> 2 | O7: =COUNTIFS(EventData!A:A,"2025",EventData!H:H,"disruption")+COUNTIFS(EventData!A:A,"2025",EventData!I:I,"disruption") -> 9 | P7: =SUM(L7:O7) -> 13 | R7: Degrade energy supply / communications infrastructure | S7: =COUNTIFS(EventData!A:A,"2022",EventData!J:J,"Degrade energy supply / communications infrastructure")+COUNTIFS(EventData!A:A,"2022",EventData!K:K,"Degrade energy supply / communications infrastructure") -> 0 | T7: =COUNTIFS(EventData!A:A,"2023",EventData!J:J,"Degrade energy supply / communications infrastructure")+COUNTIFS(EventData!A:A,"2023",EventData!K:K,"Degrade energy supply / communications infrastructure") -> 1 | U7: =COUNTIFS(EventData!A:A,"2024",EventData!J:J,"Degrade energy supply / communications infrastructure")+COUNTIFS(EventData!A:A,"2024",EventData!K:K,"Degrade energy supply / communications infrastructure") -> 3 | V7: =COUNTIFS(EventData!A:A,"2025",EventData!J:J,"Degrade energy supply / communications infrastructure")+COUNTIFS(EventData!A:A,"2025",EventData!K:K,"Degrade energy supply / communications infrastructure") -> 2 | W7: =SUM(S7:V7) -> 6 | Y7: Border | Z7: =COUNTIFS(EventData!A:A,"2022",EventData!L:L,"Border")+COUNTIFS(EventData!A:A,"2022",EventData!M:M,"Border") -> 0 | AA7: =COUNTIFS(EventData!A:A,"2023",EventData!L:L,"Border")+COUNTIFS(EventData!A:A,"2023",EventData!M:M,"Border") -> 3 | AB7: =COUNTIFS(EventData!A:A,"2024",EventData!L:L,"Border")+COUNTIFS(EventData!A:A,"2024",EventData!M:M,"Border") -> 2 | AC7: =COUNTIFS(EventData!A:A,"2025",EventData!L:L,"Border")+COUNTIFS(EventData!A:A,"2025",EventData!M:M,"Border") -> 1 | AD7: =SUM(Z7:AC7) -> 6 | AF7: Latvia | AG7: =COUNTIFS(EventData!A:A,"2022",EventData!G:G,"*latvia*") -> 2 | AH7: =COUNTIFS(EventData!A:A,"2023",EventData!G:G,"*latvia*") -> 4 | AI7: =COUNTIFS(EventData!A:A,"2024",EventData!G:G,"*latvia*") -> 3 | AJ7: =COUNTIFS(EventData!A:A,"2025",EventData!G:G,"*latvia*") -> 2 | AK7: =SUM(AG7:AJ7) -> 11
F8: 44743 | G8: =COUNTIFS(EventData!D:D,"<=" & EOMONTH(F8,0),EventData!E:E,">=" & F8) -> 4 | H8: =COUNTIFS(EventData!A:A,YEAR(F8),EventData!B:B,TEXT(F8,"mmmm"),EventData!C:C,"NO") -> 1 | I8: =SUM(G8:H8) -> 5 | K8: Arson* | L8: =COUNTIFS(EventData!A:A,"2022",EventData!H:H,"arson")+COUNTIFS(EventData!A:A,"2022",EventData!I:I,"arson") -> 0 | M8: =COUNTIFS(EventData!A:A,"2023",EventData!H:H,"arson")+COUNTIFS(EventData!A:A,"2023",EventData!I:I,"arson") -> 0 | N8: =COUNTIFS(EventData!A:A,"2024",EventData!H:H,"arson")+COUNTIFS(EventData!A:A,"2024",EventData!I:I,"arson") -> 13 | O8: =COUNTIFS(EventData!A:A,"2025",EventData!H:H,"arson")+COUNTIFS(EventData!A:A,"2025",EventData!I:I,"arson") -> 1 | P8: =SUM(L8:O8) -> 14 | R8: Disrupt (civil) aviation | S8: =COUNTIFS(EventData!A:A,"2022",EventData!J:J,"Disrupt (civil) aviation")+COUNTIFS(EventData!A:A,"2022",EventData!K:K,"Disrupt (civil) aviation") -> 1 | T8: =COUNTIFS(EventData!A:A,"2023",EventData!J:J,"Disrupt (civil) aviation")+COUNTIFS(EventData!A:A,"2023",EventData!K:K,"Disrupt (civil) aviation") -> 1 | U8: =COUNTIFS(EventData!A:A,"2024",EventData!J:J,"Disrupt (civil) aviation")+COUNTIFS(EventData!A:A,"2024",EventData!K:K,"Disrupt (civil) aviation") -> 2 | V8: =COUNTIFS(EventData!A:A,"2025",EventData!J:J,"Disrupt (civil) aviation")+COUNTIFS(EventData!A:A,"2025",EventData!K:K,"Disrupt (civil) aviation") -> 7 | W8: =SUM(S8:V8) -> 11 | Y8: Transport infrastructure | Z8: =COUNTIFS(EventData!A:A,"2022",EventData!L:L,"Transport infrastructure")+COUNTIFS(EventData!A:A,"2022",EventData!M:M,"Transport infrastructure") -> 0 | AA8: =COUNTIFS(EventData!A:A,"2023",EventData!L:L,"Transport infrastructure")+COUNTIFS(EventData!A:A,"2023",EventData!M:M,"Transport infrastructure") -> 1 | AB8: =COUNTIFS(EventData!A:A,"2024",EventData!L:L,"Transport infrastructure")+COUNTIFS(EventData!A:A,"2024",EventData!M:M,"Transport infrastructure") -> 6 | AC8: =COUNTIFS(EventData!A:A,"2025",EventData!L:L,"Transport infrastructure")+COUNTIFS(EventData!A:A,"2025",EventData!M:M,"Transport infrastructure") -> 1 | AD8: =SUM(Z8:AC8) -> 8 | AF8: Baltic Sea | AG8: =COUNTIFS(EventData!A:A,"2022",EventData!G:G,"*baltic sea*") -> 1 | AH8: =COUNTIFS(EventData!A:A,"2023",EventData!G:G,"*baltic sea*") -> 3 | AI8: =COUNTIFS(EventData!A:A,"2024",EventData!G:G,"*baltic sea*") -> 4 | AJ8: =COUNTIFS(EventData!A:A,"2025",EventData!G:G,"*baltic sea*") -> 2 | AK8: =SUM(AG8:AJ8) -> 10
F9: 44774 | G9: =COUNTIFS(EventData!D:D,"<=" & EOMONTH(F9,0),EventData!E:E,">=" & F9) -> 4 | H9: =COUNTIFS(EventData!A:A,YEAR(F9),EventData!B:B,TEXT(F9,"mmmm"),EventData!C:C,"NO") -> 0 | I9: =SUM(G9:H9) -> 4 | K9: Reconnaissance | L9: =COUNTIFS(EventData!A:A,"2022",EventData!H:H,"*recon*")+COUNTIFS(EventData!A:A,"2022",EventData!I:I,"*recon*") -> 4 | M9: =COUNTIFS(EventData!A:A,"2023",EventData!H:H,"*recon*")+COUNTIFS(EventData!A:A,"2023",EventData!I:I,"*recon*") -> 1 | N9: =COUNTIFS(EventData!A:A,"2024",EventData!H:H,"*recon*")+COUNTIFS(EventData!A:A,"2024",EventData!I:I,"*recon*") -> 6 | O9: =COUNTIFS(EventData!A:A,"2025",EventData!H:H,"*recon*")+COUNTIFS(EventData!A:A,"2025",EventData!I:I,"*recon*") -> 7 | P9: =SUM(L9:O9) -> 18 | R9: Inflict economic damage | S9: =COUNTIFS(EventData!A:A,"2022",EventData!J:J,"Inflict economic damage")+COUNTIFS(EventData!A:A,"2022",EventData!K:K,"Inflict economic damage") -> 0 | T9: =COUNTIFS(EventData!A:A,"2023",EventData!J:J,"Inflict economic damage")+COUNTIFS(EventData!A:A,"2023",EventData!K:K,"Inflict economic damage") -> 0 | U9: =COUNTIFS(EventData!A:A,"2024",EventData!J:J,"Inflict economic damage")+COUNTIFS(EventData!A:A,"2024",EventData!K:K,"Inflict economic damage") -> 12 | V9: =COUNTIFS(EventData!A:A,"2025",EventData!J:J,"Inflict economic damage")+COUNTIFS(EventData!A:A,"2025",EventData!K:K,"Inflict economic damage") -> 1 | W9: =SUM(S9:V9) -> 13 | Y9: Politician(s) | Z9: =COUNTIFS(EventData!A:A,"2022",EventData!L:L,"politician(s)")+COUNTIFS(EventData!A:A,"2022",EventData!M:M,"politician(s)") -> 1 | AA9: =COUNTIFS(EventData!A:A,"2023",EventData!L:L,"politician(s)")+COUNTIFS(EventData!A:A,"2023",EventData!M:M,"politician(s)") -> 4 | AB9: =COUNTIFS(EventData!A:A,"2024",EventData!L:L,"politician(s)")+COUNTIFS(EventData!A:A,"2024",EventData!M:M,"politician(s)") -> 4 | AC9: =COUNTIFS(EventData!A:A,"2025",EventData!L:L,"politician(s)")+COUNTIFS(EventData!A:A,"2025",EventData!M:M,"politician(s)") -> 0 | AD9: =SUM(Z9:AC9) -> 9 | AF9: Estonia | AG9: =COUNTIFS(EventData!A:A,"2022",EventData!G:G,"*estonia*") -> 1 | AH9: =COUNTIFS(EventData!A:A,"2023",EventData!G:G,"*estonia*") -> 5 | AI9: =COUNTIFS(EventData!A:A,"2024",EventData!G:G,"*estonia*") -> 2 | AJ9: =COUNTIFS(EventData!A:A,"2025",EventData!G:G,"*estonia*") -> 1 | AK9: =SUM(AG9:AJ9) -> 9
F10: 44805 | G10: =COUNTIFS(EventData!D:D,"<=" & EOMONTH(F10,0),EventData!E:E,">=" & F10) -> 5 | H10: =COUNTIFS(EventData!A:A,YEAR(F10),EventData!B:B,TEXT(F10,"mmmm"),EventData!C:C,"NO") -> 0 | I10: =SUM(G10:H10) -> 5 | K10: Sabotage* | L10: =COUNTIFS(EventData!A:A,"2022",EventData!H:H,"*sabotage*")+COUNTIFS(EventData!A:A,"2022",EventData!I:I,"*sabotage*") -> 1 | M10: =COUNTIFS(EventData!A:A,"2023",EventData!H:H,"*sabotage*")+COUNTIFS(EventData!A:A,"2023",EventData!I:I,"*sabotage*") -> 4 | N10: =COUNTIFS(EventData!A:A,"2024",EventData!H:H,"*sabotage*")+COUNTIFS(EventData!A:A,"2024",EventData!I:I,"*sabotage*") -> 16 | O10: =COUNTIFS(EventData!A:A,"2025",EventData!H:H,"*sabotage*")+COUNTIFS(EventData!A:A,"2025",EventData!I:I,"*sabotage*") -> 9 | P10: =SUM(L10:O10) -> 30 | R10: Preparation for potential sabotage | S10: =COUNTIFS(EventData!A:A,"2022",EventData!J:J,"*preparation for*")+COUNTIFS(EventData!A:A,"2022",EventData!K:K,"*preparation for*") -> 4 | T10: =COUNTIFS(EventData!A:A,"2023",EventData!J:J,"*preparation for*")+COUNTIFS(EventData!A:A,"2023",EventData!K:K,"*preparation for*") -> 1 | U10: =COUNTIFS(EventData!A:A,"2024",EventData!J:J,"*preparation for*")+COUNTIFS(EventData!A:A,"2024",EventData!K:K,"*preparation for*") -> 6 | V10: =COUNTIFS(EventData!A:A,"2025",EventData!J:J,"*preparation for*")+COUNTIFS(EventData!A:A,"2025",EventData!K:K,"*preparation for*") -> 3 | W10: =SUM(S10:V10) -> 14 | Y10: Pubic services | Z10: =COUNTIFS(EventData!A:A,"2022",EventData!L:L,"public services")+COUNTIFS(EventData!A:A,"2022",EventData!M:M,"public services") -> 0 | AA10: =COUNTIFS(EventData!A:A,"2023",EventData!L:L,"public services")+COUNTIFS(EventData!A:A,"2023",EventData!M:M,"public services") -> 0 | AB10: =COUNTIFS(EventData!A:A,"2024",EventData!L:L,"public services")+COUNTIFS(EventData!A:A,"2024",EventData!M:M,"public services") -> 8 | AC10: =COUNTIFS(EventData!A:A,"2025",EventData!L:L,"public services")+COUNTIFS(EventData!A:A,"2025",EventData!M:M,"public services") -> 2 | AD10: =SUM(Z10:AC10) -> 10 | AF10: Belgium | AG10: =COUNTIFS(EventData!A:A,"2022",EventData!G:G,"*belgium*") -> 0 | AH10: =COUNTIFS(EventData!A:A,"2023",EventData!G:G,"*belgium*") -> 2 | AI10: =COUNTIFS(EventData!A:A,"2024",EventData!G:G,"*belgium*") -> 1 | AJ10: =COUNTIFS(EventData!A:A,"2025",EventData!G:G,"*belgium*") -> 6 | AK10: =SUM(AG10:AJ10) -> 9
F11: 44835 | G11: =COUNTIFS(EventData!D:D,"<=" & EOMONTH(F11,0),EventData!E:E,">=" & F11) -> 6 | H11: =COUNTIFS(EventData!A:A,YEAR(F11),EventData!B:B,TEXT(F11,"mmmm"),EventData!C:C,"NO") -> 0 | I11: =SUM(G11:H11) -> 6 | K11: Influence operation | L11: =COUNTIFS(EventData!A:A,"2022",EventData!H:H,"*influence*")+COUNTIFS(EventData!A:A,"2022",EventData!I:I,"*influence*") -> 6 | M11: =COUNTIFS(EventData!A:A,"2023",EventData!H:H,"*influence*")+COUNTIFS(EventData!A:A,"2023",EventData!I:I,"*influence*") -> 10 | N11: =COUNTIFS(EventData!A:A,"2024",EventData!H:H,"*influence*")+COUNTIFS(EventData!A:A,"2024",EventData!I:I,"*influence*") -> 17 | O11: =COUNTIFS(EventData!A:A,"2025",EventData!H:H,"*influence*")+COUNTIFS(EventData!A:A,"2025",EventData!I:I,"*influence*") -> 10 | P11: =SUM(L11:O11) -> 43 | R11: Disrupt (military) aid to Ukraine | S11: =COUNTIFS(EventData!A:A,"2022",EventData!J:J,"Disrupt (military) aid to Ukraine")+COUNTIFS(EventData!A:A,"2022",EventData!K:K,"Disrupt (military) aid to Ukraine") -> 7 | T11: =COUNTIFS(EventData!A:A,"2023",EventData!J:J,"Disrupt (military) aid to Ukraine")+COUNTIFS(EventData!A:A,"2023",EventData!K:K,"Disrupt (military) aid to Ukraine") -> 8 | U11: =COUNTIFS(EventData!A:A,"2024",EventData!J:J,"Disrupt (military) aid to Ukraine")+COUNTIFS(EventData!A:A,"2024",EventData!K:K,"Disrupt (military) aid to Ukraine") -> 11 | V11: =COUNTIFS(EventData!A:A,"2025",EventData!J:J,"Disrupt (military) aid to Ukraine")+COUNTIFS(EventData!A:A,"2025",EventData!K:K,"Disrupt (military) aid to Ukraine") -> 4 | W11: =SUM(S11:V11) -> 30 | Y11: Energy / communications infrastructure | Z11: =COUNTIFS(EventData!A:A,"2022",EventData!L:L,"Energy / communications infrastructure")+COUNTIFS(EventData!A:A,"2022",EventData!M:M,"Energy / communications infrastructure") -> 2 | AA11: =COUNTIFS(EventData!A:A,"2023",EventData!L:L,"Energy / communications infrastructure")+COUNTIFS(EventData!A:A,"2023",EventData!M:M,"Energy / communications infrastructure") -> 2 | AB11: =COUNTIFS(EventData!A:A,"2024",EventData!L:L,"Energy / communications infrastructure")+COUNTIFS(EventData!A:A,"2024",EventData!M:M,"Energy / communications infrastructure") -> 5 | AC11: =COUNTIFS(EventData!A:A,"2025",EventData!L:L,"Energy / communications infrastructure")+COUNTIFS(EventData!A:A,"2025",EventData!M:M,"Energy / communications infrastructure") -> 5 | AD11: =SUM(Z11:AC11) -> 14 | AF11: Lithuania | AG11: =COUNTIFS(EventData!A:A,"2022",EventData!G:G,"*lithuania*") -> 0 | AH11: =COUNTIFS(EventData!A:A,"2023",EventData!G:G,"*lithuania*") -> 2 | AI11: =COUNTIFS(EventData!A:A,"2024",EventData!G:G,"*lithuania*") -> 5 | AJ11: =COUNTIFS(EventData!A:A,"2025",EventData!G:G,"*lithuania*") -> 2 | AK11: =SUM(AG11:AJ11) -> 9
F12: 44866 | G12: =COUNTIFS(EventData!D:D,"<=" & EOMONTH(F12,0),EventData!E:E,">=" & F12) -> 6 | H12: =COUNTIFS(EventData!A:A,YEAR(F12),EventData!B:B,TEXT(F12,"mmmm"),EventData!C:C,"NO") -> 0 | I12: =SUM(G12:H12) -> 6 | R12: Compromise domestic / EU politics | S12: =COUNTIFS(EventData!A:A,"2022",EventData!J:J,"Compromise domestic / EU politics")+COUNTIFS(EventData!A:A,"2022",EventData!K:K,"Compromise domestic / EU politics") -> 2 | T12: =COUNTIFS(EventData!A:A,"2023",EventData!J:J,"Compromise domestic / EU politics")+COUNTIFS(EventData!A:A,"2023",EventData!K:K,"Compromise domestic / EU politics") -> 6 | U12: =COUNTIFS(EventData!A:A,"2024",EventData!J:J,"Compromise domestic / EU politics")+COUNTIFS(EventData!A:A,"2024",EventData!K:K,"Compromise domestic / EU politics") -> 16 | V12: =COUNTIFS(EventData!A:A,"2025",EventData!J:J,"Compromise domestic / EU politics")+COUNTIFS(EventData!A:A,"2025",EventData!K:K,"Compromise domestic / EU politics") -> 8 | W12: =SUM(S12:V12) -> 32 | Y12: Civil aviation | Z12: =COUNTIFS(EventData!A:A,"2022",EventData!L:L,"Civil aviation")+COUNTIFS(EventData!A:A,"2022",EventData!M:M,"Civil aviation") -> 1 | AA12: =COUNTIFS(EventData!A:A,"2023",EventData!L:L,"Civil aviation")+COUNTIFS(EventData!A:A,"2023",EventData!M:M,"Civil aviation") -> 1 | AB12: =COUNTIFS(EventData!A:A,"2024",EventData!L:L,"Civil aviation")+COUNTIFS(EventData!A:A,"2024",EventData!M:M,"Civil aviation") -> 5 | AC12: =COUNTIFS(EventData!A:A,"2025",EventData!L:L,"Civil aviation")+COUNTIFS(EventData!A:A,"2025",EventData!M:M,"Civil aviation") -> 9 | AD12: =SUM(Z12:AC12) -> 16 | AF12: Spain | AG12: =COUNTIFS(EventData!A:A,"2022",EventData!G:G,"*spain*") -> 1 | AH12: =COUNTIFS(EventData!A:A,"2023",EventData!G:G,"*spain*") -> 2 | AI12: =COUNTIFS(EventData!A:A,"2024",EventData!G:G,"*spain*") -> 4 | AJ12: =COUNTIFS(EventData!A:A,"2025",EventData!G:G,"*spain*") -> 1 | AK12: =SUM(AG12:AJ12) -> 8
F13: 44896 | G13: =COUNTIFS(EventData!D:D,"<=" & EOMONTH(F13,0),EventData!E:E,">=" & F13) -> 6 | H13: =COUNTIFS(EventData!A:A,YEAR(F13),EventData!B:B,TEXT(F13,"mmmm"),EventData!C:C,"NO") -> 1 | I13: =SUM(G13:H13) -> 7 | K13: * Includes preparations for & attempted | R13: Disrupt daily life | S13: =COUNTIFS(EventData!A:A,"2022",EventData!J:J,"Disrupt daily life")+COUNTIFS(EventData!A:A,"2022",EventData!K:K,"Disrupt daily life") -> 1 | T13: =COUNTIFS(EventData!A:A,"2023",EventData!J:J,"Disrupt daily life")+COUNTIFS(EventData!A:A,"2023",EventData!K:K,"Disrupt daily life") -> 7 | U13: =COUNTIFS(EventData!A:A,"2024",EventData!J:J,"Disrupt daily life")+COUNTIFS(EventData!A:A,"2024",EventData!K:K,"Disrupt daily life") -> 28 | V13: =COUNTIFS(EventData!A:A,"2025",EventData!J:J,"Disrupt daily life")+COUNTIFS(EventData!A:A,"2025",EventData!K:K,"Disrupt daily life") -> 10 | W13: =SUM(S13:V13) -> 46 | Y13: Internet / Social media / News | Z13: =COUNTIFS(EventData!A:A,"2022",EventData!L:L,"Internet / Social media / news")+COUNTIFS(EventData!A:A,"2022",EventData!M:M,"Internet / Social media / news") -> 1 | AA13: =COUNTIFS(EventData!A:A,"2023",EventData!L:L,"Internet / Social media / news")+COUNTIFS(EventData!A:A,"2023",EventData!M:M,"Internet / Social media / news") -> 4 | AB13: =COUNTIFS(EventData!A:A,"2024",EventData!L:L,"Internet / Social media / news")+COUNTIFS(EventData!A:A,"2024",EventData!M:M,"Internet / Social media / news") -> 8 | AC13: =COUNTIFS(EventData!A:A,"2025",EventData!L:L,"Internet / Social media / news")+COUNTIFS(EventData!A:A,"2025",EventData!M:M,"Internet / Social media / news") -> 6 | AD13: =SUM(Z13:AC13) -> 19 | AF13: Finland | AG13: =COUNTIFS(EventData!A:A,"2022",EventData!G:G,"*finland*") -> 0 | AH13: =COUNTIFS(EventData!A:A,"2023",EventData!G:G,"*finland*") -> 2 | AI13: =COUNTIFS(EventData!A:A,"2024",EventData!G:G,"*finland*") -> 4 | AJ13: =COUNTIFS(EventData!A:A,"2025",EventData!G:G,"*finland*") -> 2 | AK13: =SUM(AG13:AJ13) -> 8
F14: 44927 | G14: =COUNTIFS(EventData!D:D,"<=" & EOMONTH(F14,0),EventData!E:E,">=" & F14) -> 7 | H14: =COUNTIFS(EventData!A:A,YEAR(F14),EventData!B:B,TEXT(F14,"mmmm"),EventData!C:C,"NO") -> 1 | I14: =SUM(G14:H14) -> 8 | K14: ** Includes plots & attempts | Y14: Military / weapons production infrastructure | Z14: =COUNTIFS(EventData!A:A,"2022",EventData!L:L,"Military / weapons production infrastructure")+COUNTIFS(EventData!A:A,"2022",EventData!M:M,"Military / weapons production infrastructure") -> 5 | AA14: =COUNTIFS(EventData!A:A,"2023",EventData!L:L,"Military / weapons production infrastructure")+COUNTIFS(EventData!A:A,"2023",EventData!M:M,"Military / weapons production infrastructure") -> 2 | AB14: =COUNTIFS(EventData!A:A,"2024",EventData!L:L,"Military / weapons production infrastructure")+COUNTIFS(EventData!A:A,"2024",EventData!M:M,"Military / weapons production infrastructure") -> 4 | AC14: =COUNTIFS(EventData!A:A,"2025",EventData!L:L,"Military / weapons production infrastructure")+COUNTIFS(EventData!A:A,"2025",EventData!M:M,"Military / weapons production infrastructure") -> 9 | AD14: =SUM(Z14:AC14) -> 20 | AF14: Italy | AG14: =COUNTIFS(EventData!A:A,"2022",EventData!G:G,"*italy*") -> 1 | AH14: =COUNTIFS(EventData!A:A,"2023",EventData!G:G,"*italy*") -> 1 | AI14: =COUNTIFS(EventData!A:A,"2024",EventData!G:G,"*italy*") -> 2 | AJ14: =COUNTIFS(EventData!A:A,"2025",EventData!G:G,"*italy*") -> 3 | AK14: =SUM(AG14:AJ14) -> 7
F15: 44958 | G15: =COUNTIFS(EventData!D:D,"<=" & EOMONTH(F15,0),EventData!E:E,">=" & F15) -> 7 | H15: =COUNTIFS(EventData!A:A,YEAR(F15),EventData!B:B,TEXT(F15,"mmmm"),EventData!C:C,"NO") -> 0 | I15: =SUM(G15:H15) -> 7 | Y15: Public space | Z15: =COUNTIFS(EventData!A:A,"2022",EventData!L:L,"*public space*")+COUNTIFS(EventData!A:A,"2022",EventData!M:M,"*public space*") -> 4 | AA15: =COUNTIFS(EventData!A:A,"2023",EventData!L:L,"*public space*")+COUNTIFS(EventData!A:A,"2023",EventData!M:M,"*public space*") -> 5 | AB15: =COUNTIFS(EventData!A:A,"2024",EventData!L:L,"*public space*")+COUNTIFS(EventData!A:A,"2024",EventData!M:M,"*public space*") -> 24 | AC15: =COUNTIFS(EventData!A:A,"2025",EventData!L:L,"*public space*")+COUNTIFS(EventData!A:A,"2025",EventData!M:M,"*public space*") -> 6 | AD15: =SUM(Z15:AC15) -> 39 | AF15: Romania | AG15: =COUNTIFS(EventData!A:A,"2022",EventData!G:G,"*romania*") -> 0 | AH15: =COUNTIFS(EventData!A:A,"2023",EventData!G:G,"*romania*") -> 1 | AI15: =COUNTIFS(EventData!A:A,"2024",EventData!G:G,"*romania*") -> 3 | AJ15: =COUNTIFS(EventData!A:A,"2025",EventData!G:G,"*romania*") -> 3 | AK15: =SUM(AG15:AJ15) -> 7
F16: 44986 | G16: =COUNTIFS(EventData!D:D,"<=" & EOMONTH(F16,0),EventData!E:E,">=" & F16) -> 8 | H16: =COUNTIFS(EventData!A:A,YEAR(F16),EventData!B:B,TEXT(F16,"mmmm"),EventData!C:C,"NO") -> 1 | I16: =SUM(G16:H16) -> 9 | AF16: Czechia | AG16: =COUNTIFS(EventData!A:A,"2022",EventData!G:G,"*czechia*") -> 0 | AH16: =COUNTIFS(EventData!A:A,"2023",EventData!G:G,"*czechia*") -> 1 | AI16: =COUNTIFS(EventData!A:A,"2024",EventData!G:G,"*czechia*") -> 3 | AJ16: =COUNTIFS(EventData!A:A,"2025",EventData!G:G,"*czechia*") -> 1 | AK16: =SUM(AG16:AJ16) -> 5
F17: 45017 | G17: =COUNTIFS(EventData!D:D,"<=" & EOMONTH(F17,0),EventData!E:E,">=" & F17) -> 7 | H17: =COUNTIFS(EventData!A:A,YEAR(F17),EventData!B:B,TEXT(F17,"mmmm"),EventData!C:C,"NO") -> 0 | I17: =SUM(G17:H17) -> 7 | AF17: Bulgaria | AG17: =COUNTIFS(EventData!A:A,"2022",EventData!G:G,"*bulgaria*") -> 1 | AH17: =COUNTIFS(EventData!A:A,"2023",EventData!G:G,"*bulgaria*") -> 2 | AI17: =COUNTIFS(EventData!A:A,"2024",EventData!G:G,"*bulgaria*") -> 1 | AJ17: =COUNTIFS(EventData!A:A,"2025",EventData!G:G,"*bulgaria*") -> 1 | AK17: =SUM(AG17:AJ17) -> 5
F18: 45047 | G18: =COUNTIFS(EventData!D:D,"<=" & EOMONTH(F18,0),EventData!E:E,">=" & F18) -> 6 | H18: =COUNTIFS(EventData!A:A,YEAR(F18),EventData!B:B,TEXT(F18,"mmmm"),EventData!C:C,"NO") -> 1 | I18: =SUM(G18:H18) -> 7 | AF18: Sweden | AG18: =COUNTIFS(EventData!A:A,"2022",EventData!G:G,"*sweden*") -> 0 | AH18: =COUNTIFS(EventData!A:A,"2023",EventData!G:G,"*sweden*") -> 1 | AI18: =COUNTIFS(EventData!A:A,"2024",EventData!G:G,"*sweden*") -> 2 | AJ18: =COUNTIFS(EventData!A:A,"2025",EventData!G:G,"*sweden*") -> 2 | AK18: =SUM(AG18:AJ18) -> 5
F19: 45078 | G19: =COUNTIFS(EventData!D:D,"<=" & EOMONTH(F19,0),EventData!E:E,">=" & F19) -> 7 | H19: =COUNTIFS(EventData!A:A,YEAR(F19),EventData!B:B,TEXT(F19,"mmmm"),EventData!C:C,"NO") -> 0 | I19: =SUM(G19:H19) -> 7 | AF19: Austria | AG19: =COUNTIFS(EventData!A:A,"2022",EventData!G:G,"*austria*") -> 1 | AH19: =COUNTIFS(EventData!A:A,"2023",EventData!G:G,"*austria*") -> 1 | AI19: =COUNTIFS(EventData!A:A,"2024",EventData!G:G,"*austria*") -> 1 | AJ19: =COUNTIFS(EventData!A:A,"2025",EventData!G:G,"*austria*") -> 1 | AK19: =SUM(AG19:AJ19) -> 4
F20: 45108 | G20: =COUNTIFS(EventData!D:D,"<=" & EOMONTH(F20,0),EventData!E:E,">=" & F20) -> 7 | H20: =COUNTIFS(EventData!A:A,YEAR(F20),EventData!B:B,TEXT(F20,"mmmm"),EventData!C:C,"NO") -> 1 | I20: =SUM(G20:H20) -> 8 | AF20: Switzerland | AG20: =COUNTIFS(EventData!A:A,"2022",EventData!G:G,"*switzerland*") -> 0 | AH20: =COUNTIFS(EventData!A:A,"2023",EventData!G:G,"*switzerland*") -> 1 | AI20: =COUNTIFS(EventData!A:A,"2024",EventData!G:G,"*switzerland*") -> 2 | AJ20: =COUNTIFS(EventData!A:A,"2025",EventData!G:G,"*switzerland*") -> 1 | AK20: =SUM(AG20:AJ20) -> 4
F21: 45139 | G21: =COUNTIFS(EventData!D:D,"<=" & EOMONTH(F21,0),EventData!E:E,">=" & F21) -> 10 | H21: =COUNTIFS(EventData!A:A,YEAR(F21),EventData!B:B,TEXT(F21,"mmmm"),EventData!C:C,"NO") -> 0 | I21: =SUM(G21:H21) -> 10 | AF21: Denmark | AG21: =COUNTIFS(EventData!A:A,"2022",EventData!G:G,"*denmark*") -> 0 | AH21: =COUNTIFS(EventData!A:A,"2023",EventData!G:G,"*denmark*") -> 0 | AI21: =COUNTIFS(EventData!A:A,"2024",EventData!G:G,"*denmark*") -> 1 | AJ21: =COUNTIFS(EventData!A:A,"2025",EventData!G:G,"*denmark*") -> 3 | AK21: =SUM(AG21:AJ21) -> 4
F22: 45170 | G22: =COUNTIFS(EventData!D:D,"<=" & EOMONTH(F22,0),EventData!E:E,">=" & F22) -> 11 | H22: =COUNTIFS(EventData!A:A,YEAR(F22),EventData!B:B,TEXT(F22,"mmmm"),EventData!C:C,"NO") -> 0 | I22: =SUM(G22:H22) -> 11 | AF22: Norway | AG22: =COUNTIFS(EventData!A:A,"2022",EventData!G:G,"*norway*") -> 1 | AH22: =COUNTIFS(EventData!A:A,"2023",EventData!G:G,"*norway*") -> 0 | AI22: =COUNTIFS(EventData!A:A,"2024",EventData!G:G,"*norway*") -> 0 | AJ22: =COUNTIFS(EventData!A:A,"2025",EventData!G:G,"*norway*") -> 2 | AK22: =SUM(AG22:AJ22) -> 3
F23: 45200 | G23: =COUNTIFS(EventData!D:D,"<=" & EOMONTH(F23,0),EventData!E:E,">=" & F23) -> 11 | H23: =COUNTIFS(EventData!A:A,YEAR(F23),EventData!B:B,TEXT(F23,"mmmm"),EventData!C:C,"NO") -> 2 | I23: =SUM(G23:H23) -> 13 | AF23: North Sea | AG23: =COUNTIFS(EventData!A:A,"2022",EventData!G:G,"*north sea*") -> 1 | AH23: =COUNTIFS(EventData!A:A,"2023",EventData!G:G,"*north sea*") -> 1 | AI23: =COUNTIFS(EventData!A:A,"2024",EventData!G:G,"*north sea*") -> 1 | AJ23: =COUNTIFS(EventData!A:A,"2025",EventData!G:G,"*north sea*") -> 0 | AK23: =SUM(AG23:AJ23) -> 3
F24: 45231 | G24: =COUNTIFS(EventData!D:D,"<=" & EOMONTH(F24,0),EventData!E:E,">=" & F24) -> 11 | H24: =COUNTIFS(EventData!A:A,YEAR(F24),EventData!B:B,TEXT(F24,"mmmm"),EventData!C:C,"NO") -> 2 | I24: =SUM(G24:H24) -> 13 | AF24: Ireland | AG24: =COUNTIFS(EventData!A:A,"2022",EventData!G:G,"*Ireland*") -> 1 | AH24: =COUNTIFS(EventData!A:A,"2023",EventData!G:G,"*ireland*") -> 0 | AI24: =COUNTIFS(EventData!A:A,"2024",EventData!G:G,"*ireland*") -> 0 | AJ24: =COUNTIFS(EventData!A:A,"2025",EventData!G:G,"*ireland*") -> 1 | AK24: =SUM(AG24:AJ24) -> 2
F25: 45261 | G25: =COUNTIFS(EventData!D:D,"<=" & EOMONTH(F25,0),EventData!E:E,">=" & F25) -> 11 | H25: =COUNTIFS(EventData!A:A,YEAR(F25),EventData!B:B,TEXT(F25,"mmmm"),EventData!C:C,"NO") -> 2 | I25: =SUM(G25:H25) -> 13 | AF25: Slovakia | AG25: =COUNTIFS(EventData!A:A,"2022",EventData!G:G,"*slovakia*") -> 0 | AH25: =COUNTIFS(EventData!A:A,"2023",EventData!G:G,"*slovakia*") -> 0 | AI25: =COUNTIFS(EventData!A:A,"2024",EventData!G:G,"*slovakia*") -> 1 | AJ25: =COUNTIFS(EventData!A:A,"2025",EventData!G:G,"*slovakia*") -> 0 | AK25: =SUM(AG25:AJ25) -> 1
F26: 45292 | G26: =COUNTIFS(EventData!D:D,"<=" & EOMONTH(F26,0),EventData!E:E,">=" & F26) -> 9 | H26: =COUNTIFS(EventData!A:A,YEAR(F26),EventData!B:B,TEXT(F26,"mmmm"),EventData!C:C,"NO") -> 5 | I26: =SUM(G26:H26) -> 14
F27: 45323 | G27: =COUNTIFS(EventData!D:D,"<=" & EOMONTH(F27,0),EventData!E:E,">=" & F27) -> 10 | H27: =COUNTIFS(EventData!A:A,YEAR(F27),EventData!B:B,TEXT(F27,"mmmm"),EventData!C:C,"NO") -> 2 | I27: =SUM(G27:H27) -> 12
F28: 45352 | G28: =COUNTIFS(EventData!D:D,"<=" & EOMONTH(F28,0),EventData!E:E,">=" & F28) -> 10 | H28: =COUNTIFS(EventData!A:A,YEAR(F28),EventData!B:B,TEXT(F28,"mmmm"),EventData!C:C,"NO") -> 6 | I28: =SUM(G28:H28) -> 16
F29: 45383 | G29: =COUNTIFS(EventData!D:D,"<=" & EOMONTH(F29,0),EventData!E:E,">=" & F29) -> 9 | H29: =COUNTIFS(EventData!A:A,YEAR(F29),EventData!B:B,TEXT(F29,"mmmm"),EventData!C:C,"NO") -> 5 | I29: =SUM(G29:H29) -> 14
F30: 45413 | G30: =COUNTIFS(EventData!D:D,"<=" & EOMONTH(F30,0),EventData!E:E,">=" & F30) -> 9 | H30: =COUNTIFS(EventData!A:A,YEAR(F30),EventData!B:B,TEXT(F30,"mmmm"),EventData!C:C,"NO") -> 8 | I30: =SUM(G30:H30) -> 17
F31: 45444 | G31: =COUNTIFS(EventData!D:D,"<=" & EOMONTH(F31,0),EventData!E:E,">=" & F31) -> 8 | H31: =COUNTIFS(EventData!A:A,YEAR(F31),EventData!B:B,TEXT(F31,"mmmm"),EventData!C:C,"NO") -> 6 | I31: =SUM(G31:H31) -> 14
F32: 45474 | G32: =COUNTIFS(EventData!D:D,"<=" & EOMONTH(F32,0),EventData!E:E,">=" & F32) -> 7 | H32: =COUNTIFS(EventData!A:A,YEAR(F32),EventData!B:B,TEXT(F32,"mmmm"),EventData!C:C,"NO") -> 8 | I32: =SUM(G32:H32) -> 15
F33: 45505 | G33: =COUNTIFS(EventData!D:D,"<=" & EOMONTH(F33,0),EventData!E:E,">=" & F33) -> 7 | H33: =COUNTIFS(EventData!A:A,YEAR(F33),EventData!B:B,TEXT(F33,"mmmm"),EventData!C:C,"NO") -> 4 | I33: =SUM(G33:H33) -> 11
F34: 45536 | G34: =COUNTIFS(EventData!D:D,"<=" & EOMONTH(F34,0),EventData!E:E,">=" & F34) -> 6 | H34: =COUNTIFS(EventData!A:A,YEAR(F34),EventData!B:B,TEXT(F34,"mmmm"),EventData!C:C,"NO") -> 2 | I34: =SUM(G34:H34) -> 8
F35: 45566 | G35: =COUNTIFS(EventData!D:D,"<=" & EOMONTH(F35,0),EventData!E:E,">=" & F35) -> 6 | H35: =COUNTIFS(EventData!A:A,YEAR(F35),EventData!B:B,TEXT(F35,"mmmm"),EventData!C:C,"NO") -> 1 | I35: =SUM(G35:H35) -> 7
F36: 45597 | G36: =COUNTIFS(EventData!D:D,"<=" & EOMONTH(F36,0),EventData!E:E,">=" & F36) -> 8 | H36: =COUNTIFS(EventData!A:A,YEAR(F36),EventData!B:B,TEXT(F36,"mmmm"),EventData!C:C,"NO") -> 3 | I36: =SUM(G36:H36) -> 11
F37: 45627 | G37: =COUNTIFS(EventData!D:D,"<=" & EOMONTH(F37,0),EventData!E:E,">=" & F37) -> 8 | H37: =COUNTIFS(EventData!A:A,YEAR(F37),EventData!B:B,TEXT(F37,"mmmm"),EventData!C:C,"NO") -> 3 | I37: =SUM(G37:H37) -> 11
... F46: 45901 | G46: =COUNTIFS(EventData!D:D,"<=" & EOMONTH(F46,0),EventData!E:E,">=" & F46) -> 6 | H46: =COUNTIFS(EventData!A:A,YEAR(F46),EventData!B:B,TEXT(F46,"mmmm"),EventData!C:C,"NO") -> 6 | I46: =SUM(G46:H46) -> 12
B47: NB: 1 incident in 2024 had no month, excluded from figure | F47: 45931 | G47: =COUNTIFS(EventData!D:D,"<=" & EOMONTH(F47,0),EventData!E:E,">=" & F47) -> 7 | H47: =COUNTIFS(EventData!A:A,YEAR(F47),EventData!B:B,TEXT(F47,"mmmm"),EventData!C:C,"NO") -> 5 | I47: =SUM(G47:H47) -> 12
F48: 45962 | G48: =COUNTIFS(EventData!D:D,"<=" & EOMONTH(F48,0),EventData!E:E,">=" & F48) -> 7 | H48: =COUNTIFS(EventData!A:A,YEAR(F48),EventData!B:B,TEXT(F48,"mmmm"),EventData!C:C,"NO") -> 4 | I48: =SUM(G48:H48) -> 11
F49: 45992 | G49: =COUNTIFS(EventData!D:D,"<=" & EOMONTH(F49,0),EventData!E:E,">=" & F49) -> 7 | H49: =COUNTIFS(EventData!A:A,YEAR(F49),EventData!B:B,TEXT(F49,"mmmm"),EventData!C:C,"NO") -> 2 | I49: =SUM(G49:H49) -> 9
F51: NB: | G51: 1 unknown month for 2024

Sheet CategoricalVariables
A1: Variabe | B1: Option 1 | C1: Option 2 | D1: Option 3 | E1: Option 4 | F1: Option 5 | G1: Option 6 | H1: Option 7 | I1: Option 8 | J1: Option 9 | K1: Option 10 | L1: Option 11 | M1: Option 12 | N1: Option 13 | O1: Option 14 | P1: Option 15 | Q1: Option 16
A2: EventCategory | B2: Sabotage | C2: Sabotage (preparation) | D2: Sabotage (attempt) | E2: Disruptive immigration | F2: Terrorism | G2: Influence operation | H2: Assassination | I2: Assassination (plot) | J2: Assassination (attempt) | K2: Vandalism | L2: Disruption | M2: Arson | N2: Reconnaissance | O2: Unknown | P2: Does not apply
A3: ApparentGoal | B3: Disrupt daily life | C3: Degrade energy supply / communications infrastructure | D3: Disrupt (military) aid to Ukraine | E3: Disrupt (civil) aviation | F3: Inflict economic damage | G3: Kill politician / head of state | H3: Degrade military infrastructure | I3: Dissuade defection | J3: Compromise public utilities | K3: Compromise domestic / EU politics | L3: Intimidate politician / journalist | M3: Preparation for potential sabotage | N3: Unknown | O3: Does not apply
A4: TargetType | B4: Energy / communications infrastructure | C4: Transport infrastructure | D4: Border | E4: Arms deliveries to Ukraine | F4: Public space: Shopping centre / Memorial / Landmark / Company / School | G4: Military / weapons production infrastructure | H4: Civil aviation | I4: Politician(s) / Official(s) | J4: Industrialist(s) | K4: Defector(s) | L4: Journalist(s) | M4: Public services | N4: Internet / Social media / News | O4: Economic infrastructure | P4: Does not apply | Q4: Unknown
A5: IncidentMonth | B5: January | C5: February | D5: March | E5: April | F5: May | G5: June | H5: July | I5: August | J5: September | K5: October | L5: November | M5: December | N5: Unknown | O5: Does not apply
A6: IncidentYear | B6: 2022 | C6: 2023 | D6: 2024 | E6: 2025
A7: Binary | B7: Yes | C7: No
A8: DisposableAgentsInvolved | B8: Yes | C8: No | D8: Unknown
C28: `

Sheet Excluded
A1: ExIncidentYear | B1: ExIncidentMonth | C1: CountriesAffected | D1: Excluded incidents* | E1: (Link with) additional information
A2: 2021 | B2: Does not apply | C2: Poland | D2: Illegal immigration sent towards Poland by Russia / Belarus, since 2021 ie before invasion
A3: 2022 | B3: January | C3: Norway | D3: One of two cables connecting Spitsbergen to mainland Norway cut | E3: Investigation cannot prove who was responsible, no official claims of Russian involvement.
A4: 2022 | B4: April | C4: France | D4: Long-distance internet cables cut around Paris. Perpetrators remain unknown | E4: Attack of some sophistication, could point to state actor. But anti-5G / environmentalists / etc. cannot be ruled out.
A5: 2022 | B5: May | C5: Greece | D5: May 2022 fire in Piraeus, Greece, causes loss of tons of clothing aid for Ukraine | E5: Cause stated as under investigaiton, no update found, no allegations of Russian involvement.
A6: 2022 | B6: September | C6: Baltic Sea | D6: Nord Stream 1&2 sabotage | E6: Potential involvement Ukrainians rules out inclusion
A7: 2022 | B7: October | C7: Germany | D7: October 2022 German rail sabotage - no sign of state involvement, say German police
A8: 2022 | B8: October | C8: Denmark | D8: Bornholm (Denmark) power cut 2022 | E8: Appears non-sabotage related.
A9: 2022 | B9: October | C9: France | D9: October 2022 internet cable sabotage near Marseille, France. | E9: Very little info online. Russia mentioned as potential perpetrator. One of several such cuts taking place in same time period. But no clear evidence .
A10: 2022 | B10: October | C10: United Kingdom | D10: Subsea cables Faroe-Shetland and Shetland - mainland Scotland cut. BBC labels it an accident, other sources unsure. | E10: Without clearer links to Russia, has to remain 'excluded' for now.
A11: 2022 | B11: November | C11: Latvia | D11: Latvian Aivo Peterson & co allegedly worked to create 'civil defense' unit to replace the army in event of power vacuum, sought contact with Ru intel for guidance. Began November 2022, arrested 2023. | E11: Not included, because the operaiton was not Russian led but a local initiative.
A12: 2022 | B12: Does not apply | C12: Germany | D12: 2022 drone spionage of Ukrainian troops being trained in Germany | E12: No clear link to sabotage (prep) or other physical measures; appears to be more in line with classical spionage for intelligence gathering. | F12: See this link for multiple similar events.
A13: 2022 | B13: Unknown | C13: Belgium | D13: 2022: #DeCrooMustGo hashtag used in Belgium, also by pro-Russian accounts / bots | E13: Seems like some pro-Russian accounts jumped on this hashtag rather than were its originators. Too little to go on.
A14: 2023 | B14: August | C14: Poland | D14: Hackers disrupt Polish railway system | E14: Investigation has not revealed clear links to Russia, may have been hobbyists pulling an extensive prank.
A15: 2023 | B15: November | C15: Germany | D15: Nov 2023 Brunsbüttel LNG pipeline sabotage | E15: No clear link to Russia. Some suggestion of involvement climate activists.
A16: 2023 | B16: December | C16: Sweden | D16: Swedish train derailment December 2023 - likely due to climate change, not sabotage
A17: 2024 | B17: February | C17: Sweden | D17: Swedish train derailment February 2024 - likely due to climate change, not sabotage
A18: 2024 | B18: March | C18: United Kingdom | D18: British defense minister plane GPS jammed over Poland - already captured by general GPS jamming entry
A19: 2024 | B19: March | C19: Lithuania | D19: Assassination attempt / assault on Leonid Volkov | E19: Excluded because this appears part of longer-standing Russian attacks on political opposition abroad, rather than something directly linked to the war in Ukraine or Europe's support for Ukraine
A20: 2024 | B20: April | C20: United Kingdom | D20: Arms plant fires in Wales, BAE systems Glascoed, April 2024. | E20: Incident appears to be still under investigation.
A21: 2024 | B21: April | C21: Czechia | D21: April 2024, Czech news site is hacked and fake story placed about Ukrainians attempting to assassinate Slovak president | E21: No evidence or authority-based suggestion of Russian involvement, even though that seems likely
A22: 2024 | B22: May | C22: Germany | D22: Claim that Russia searched the web for perpetrator / location ahead of 2024 Mannheim stabbing attack, suggesting involvement | E22: BND voiced concerns over accuracy of method used to establish potential Russian link. No public claims by authorities so far. To be monitored.
A23: 2024 | B23: June | C23: Poland | D23: Mesko, Poland arms factory explosion, June 2024. No external force - Tusk
A24: 2024 | B24: July | C24: France | D24: Railway sabotage in France ahead of 2024 Olympics - Far Left suspected | E24: Investigation appears ongoing.
A25: 2024 | B25: July | C25: France | D25: Multiple acts of sabotage to fibre-optic (internet) cables across France, simultaneously with railway sabotage | E25: Idem. News reporting does not make clear suggestion of Russian involvement. Could also be far-left, perhaps with Russia behind them.
A26: 2024 | B26: July | C26: United States | D26: July 2024, AIVD and FBI and partners disrupt Russia-linked digital election interference targeting US | E26: Not an operation focused on Europe.
A27: 2024 | B27: September | C27: Sweden | D27: Drones sighted over Stockholm Arland airport, September 2024 - no allegation of Russian involvement
A28: 2024 | B28: September | C28: The Netherlands | D28: May 2025: revealed that Russian 'Laundry Bear' group behind hack of Dutch police in 2024 | E28: Pure cyber op. No signs of preps for sabotage linked to this hack.
A29: 2024 | B29: October | C29: United Kingdom | D29: Fire at BAE systems nuclear shipyard, 30 October 2024 - Ruled industrial accident
A30: 2024 | B30: November | C30: United Kingdom | D30: Drones spotted over UK bases, November 2024 - no (clear) sign or allegation of Russian involvement
A31: 2024 | B31: November | C31: Moldova | D31: 2024 Russian interference in Moldova's elections / drone incursions | E31: Does not appear to be related to invasion of Ukraine, rather part of broader Russian ambition of maintaining / increasing control over former Soviet states
A32: 2024 | B32: December | C32: Finland; Sweden | D32: December 2024 damage to Internet cable between Finland and Sweden | E32: Turns out to be non-sabotage related
A33: 2024 | B33: December | C33: Baltic Sea | D33: Signal flare fired at German helicopter by Russian vessel in Baltic sea, December 2024 | E33: Exaggerated instance of long-standing practice of aggressively crossing into territorial airspace, etc.
A34: 2024 | B34: December | C34: Germany | D34: December 2024 drone incursions Ramstein airforce base, Rheinmetall facilities | E34: No clear link to Russia, not clear that this was sabotage-prep rather than general surveillance.
A35: 2024 | B35: December | C35: Germany | D35: Drones spotted above Manching airbase, Ingolstadt, Bavaria, early 2025 | E35: Ibid: seems uptick in drone incursions is clear, but link to Russia and to sabotage-prep as motive is too tenuous
A36: 2024 | B36: December | C36: Germany | D36: Drones spotted over Neuburg an der Donau military base | E36: Ibid: seems uptick in drone incursions is clear, but link to Russia and to sabotage-prep as motive is too tenuous
A37: 2024 | B37: Does not apply | C37: Various | D37: Thousand of cyber attacks against EU government websites, transportation infrastructure, etc. Covers 2024
A38: 2024 | B38: Does not apply | C38: United Kingdom | D38: 2024 plot to kidnap / kill Russian opposition journalist Roman Dobrokhotov | E38: No clear link to invasion of Ukraine, target suggest this is part of wider / longer-running campaign by Moscow to silence / kill opposition (journalists).
A39: 2024 | B39: Unknown | C39: Germany | D39: Metal filings in engine of Germany Navy corvette 'Emden', late 2024 | E39: Idem
A40: 2024 | B40: Unknown | C40: Germany | D40: Mine hunter of Germany Navy damaged while docked in the Tamsen dockyard in Rostock, sabotage suspected | E40: Idem
A41: 2025 | B41: January | C41: Denmark | D41: Drone incurions Koge, Denmark, 9-10 January | E41: Police claim no evidence of military surveillance as goal
A42: 2025 | B42: January | C42: Germany | D42: Drones spotted above Manching airbase, Ingolstadt, Bavaria, early 2025 | E42: Ibid: seems uptick in drone incursions is clear, but link to Russia and to sabotage-prep as motive is too tenuous
A43: 2025 | B43: January | C43: Sweden;Latvia | D43: January 26, 2025 LVRTC cable between Sweden and Latvia damaged | E43: February 25: authorities rule out sabotage. Appears to be ship called Vezhen involved
A44: 2025 | B44: February | C44: Germany | D44: Oil injected in water tank of Germany Navy ship 'Hessen', February 2025 | E44: No (clear) sign of Russian involvement yet, see link.
A45: 2025 | B45: February | C45: United Kingdom | D45: Russia-linked Telegram channels offering to pay for attacks on Mosques in UK, February 2025 | E45: No official confirmation, report comes from an NGO, not a government source.
A46: 2025 | B46: February | C46: Lithuania | D46: February 2025: Lithuanian petition to ban Russian train transit in Lithuania possibly an influence operation | E46: One source mentions the possibilty of an influence operation no other supporting articles
A47: 2025 | B47: March | C47: Italy | D47: March 2025: drone overflight of European Joint Research Centre in Ispra, Italy. | E47: Investigation indicates drone of Russian origin, but no further detail or links to Russia. Also: espionage appeared to be goal rather than sabotage prep, so borderline in terms of whether it would fit the inclusion criteria of this dataset.
A48: 2025 | B48: March | C48: Germany | D48: March 2025: German intel services see it as theoretical possibility that Russia was involved in increased number of terrorist attacks prior to 2025 German elections | E48: Only a theory, no evidence
A49: 2025 | B49: March | C49: North Sea | D49: March 2025: Oil tanker Stena Immaculate carrying jet fuel hit by container ship Solong off British coast, master is Russian national | E49: UK claimed no no evidence of foul play, though very odd incident to happen | F49: Early reports suggest very poor visibility and lack of lookouts may have played role.
A50: 2025 | B50: March | C50: Czechia | D50: March 2025: explosion at Czech ammunition plant / warehouse Policske Strojirny ruled accident
A51: 2025 | B51: March | C51: The Netherlands | D51: March 2025 stabbing attack in Amsterdam by Ukrainian deserter Roman D. | E51: No apparent links to Russia.
A52: 2025 | B52: April | C52: United Kingdom | D52: April 2025: news of Russian spying on British Vanguard nuclear submarines | E52: Espionage is ongoing, not clearly enough related to war in Ukraine linked hybrid operations
A53: 2025 | B53: April | C53: Sweden | D53: Easter 2025 sabotage to telecom masts / infrastructure in Sweden along E22 highway. 30 instances. | E53: No clear link to Russia, investigators seems to float option it could also be anti-5G activists
A54: 2025 | B54: May | C54: France | D54: May 2025: two power cuts in Cannes area, France. Sabotage suspected, Anarchist groups claim responsibility
A56: 2025 | B56: June | C56: Germany | D56: 4 Bundeswehr (Army / military) trucks destroyed in fire. Arson suspected, claimed on Pro-Russian telegram channels. | E56: Claims may be opportunistic. No official claim of link to Russia. Two similar army truck arsons linked to / claimed by far-left group Agenda2029. | F56: Here source claims unrelated to Ukraine
A57: 2025 | B57: June | C57: Hungary / Ukraine | D57: Russian attempt to incite ethnic Hungarians in Ukrainian Transcarpathia to engage in revolt/terrorism | E57: Operation aimed against Ukraine, not Hungary (ie, outside of scope of this project which looks at Russian ops against Europe beyond Ukraine).
A58: 2025 | B58: July | C58: Poland | D58: Series of fires / arsons (Siemianowice Śląskie, in southern Poland, production hall in Mińsk Mazowiecki, Zabki) | E58: Authorities don't actually link these to Russia (yet), but suggest they may be sabotage given 2024 arsons that were indeed orchestrated by Russia.
A59: 2025 | B59: June | C59: Germany | D59: 12 injured after contact with powder in DHL depot Langenzenn | E59: No clear link with Russia
A60: 2025 | B60: August | C60: Poland | D60: Artem K. offered services to Belarus | E60: Not (technically) a Russian hybrid OP.
A61: 2025 | B61: September | C61: Poland | D61: Two Belarussians arrested for flying drone over presidential palace | E61: Unclear what motives were. As of yet no sign that this was sabotage prep.
A62: 2025 | B62: September | C62: Bulgaria | D62: EU President Von der Leyen's plan subject to GPS jamming | E62: Unclear whether this plane was targeted specifically, or fits in already accounted-for GPS jamming activities that affect large number of aircraft.
A63: 2025 | B63: September | C63: United Kingdom | D63: Three arrested on suspicion of spying for Russia | E63: Spying, not sabotage/influence/etc. ops.
A64: 2024 | B64: May | C64: Germany | D64: Fire in Diehl Metall plant ruled out as sabotage-related
A65: 2025 | B65: September | C65: UK; Belgium | D65: Ransomware attack that crippled Heathrow and Brussels airport may have been caused by 'Everest Group', who some source allege to be Russian/Russian speaking. | E65: As of 24 October 2025; no official claims of Everest Group involvement or links to Russia. Leaving excluded for now.
A66: 2025 | B66: September | C66: Germany | D66: Suspected sabotage of signal box (stellwerk) on railway line between Cologne and Dusseldorf | E66: As of 24 October, no update to suggest who was responsible. Leaving excluded for now.
A67: 2025 | B67: September | C67: Norway;Denmark; North Sea | D67: Multiple other drone sightings, e.g. Orland airbase Norway, Sleipner gas field | E67: Links to Russia for the more widely-reported drone sightings in September are already circumstantial. Leaving these apparently even less well-covered / less plausibly linked to Russia incidents outside of analysis for now.
A68: 2025 | B68: October | C68: Germany | D68: AfD accused by interior minister for Thuringen of spying for Russia using parliamentary inquiries | E68: Unclear if related specifically to Russian invasion Ukraine. See also: https://nos.nl/artikel/2589346-duitse-partijen-verdenken-afd-openlijk-van-spionage-voor-rusland
A69: 2025 | B69: November | C69: Germany | D69: Potential drone sighting over Bremen airport | E69: Seems too 'potential'.
A70: 2025 | B70: November | C70: Germany | D70: Potential drone sighting over Berlin airport | E70: Idem.
A71: 2025 | B71: October | C71: Spain | D71: Drone sighting Palma de Mallorca airport | E71: Too unclear whether this is part of Russia-linked drone wave. Geographical outlier and no conclusive reporting providing such a link.
A72: 2025 | B72: September | C72: Norway | D72: Drones spotted near Oslo airport lead to shut downs, Monday 22 September - 23 September | E72: Removed because in early November, Norwegian police closed the investigation due to lack of evidence that drones had or had not been sighted.
A73: 2025 | B73: October | C73: Poland | D73: Drones disrupt Dutch soldiers on excercise in Poland. | E73: Removed because remains too unclear whther this is linked to Russia. Some reports suggest drones coming from Belarussia.
A74: 2025 | B74: September | C74: Denmark | D74: Drones sighted at Copenhagen airport, 22-23 September | E74: Removed because internal memo suggests air traffic controllers did not actually seen drones. Too much uncertainty to include.
A75: 2025 | B75: November | C75: Belgium | D75: Drones sighted at Brussels/Zaventem airport (4 NOV), military facilities Heverlee (5 NOV), airbase Melsbroek (6NOV) debunked
A76: 2025 | B76: May | C76: United Kingdom | D76: May 2025 fires at homes linked to British PM Keir Starmer. Being investigated for potential link to Russia.
A77: 2025 | B77: October | C77: Czechia | D77: Czech republic reports on 10 October increasing number of drones flying over military facilities. But no link made to Russia
A78: 2025 | B78: November | C78: Netherlands | D78: Drone sightings / attempted shoot downs Volkel air base | E78: Evidence of drones actually being there, and of Russian operators, lacking.
A79: 2025 | B79: September | C79: Denmark | D79: Drones spotted near Copenhagen airport lead to shut downs, Monday 22 September - 23 September | E79: OSINT community has plausible evidence that drone sighting in Denmarkt was actually a small plane. Airport did not have drone detection equipment yet that night. Excluded unless evidence hardens up
A80: 2025 | B80: December | C80: Germany | D80: Drones over Immelmann barracks, Germany | E80: No clear link with Russia
A81: 2025 | B81: November | C81: Denmark | D81: Election interference by cyber (DDOS?) attack against websites linked to Danish political parties | E81: No clear physical effect or disinfo campaign
D88: * No clear link with Russia (e.g., no govermental allegation or speculation, variety of causes hypothesized, etc.)

Sheet DroneSightingsQ4_2025
A1: Explanation | B1: As investigative / OSINT reporting by Dutch newspaper Trouw and dronewatch.nl suggest, of the 60+ drone sightings in Europe between September and December 2025, the vast majority are unconfirmed, and a growing number seem to be based on faulty observations or even 'drone panic'. I have kept only those incidents where authorities believe there is a strong case for suspecting Russian involvement; several sightings in Belgium, Denmark, Norway, and Ireland. I would not be surprised if the majority of these 'confirmed' incidents are also going to be debunked, as has already happened with some in Belgium (https://www.vrt.be/vrtnws/nl/2025/11/12/check-drones-zaventem-heverlee-melsbroek-helikopter-vliegtuig/). But this approach seems to me a defensible median between accepting all sightings as having a link to Russia and saying none of them do. The latter position seems unlikely to me, even if there are -to my mind- elements of a 'drone panic' in the suddenly very large number of sightings but very limited degree of confirmatory evidence (e.g., clear photos). For more details, see: https://www.dronewatch.nl/2025/11/28/61-europese-dronewaarnemingen-geanalyseerd-dit-weten-we-nu/.
B3: Links to (tentative) official confirmation of link with Russia / hybrid warfare
A4: Belgium | B4: https://www.vrt.be/vrtnws/en/2025/11/05/belgian-security-services-convinced-russia-is-behind-the-drone-i/
A5: Denmark | B5: https://www.france24.com/en/europe/20250927-new-drones-sighted-over-denmark-s-largest-military-base
A6: Norway (confirmed by EU commission) | B6: https://nos.nl/artikel/2584475-vluchten-omgeleid-in-noorwegen-na-dronewaarnemingen
A7: Germany | B7: https://www.politico.eu/article/germany-friedrich-merz-suspects-kremlin-behind-drone-sightings-munich/
B8: https://nos.nl/artikel/2584784-verdachte-drones-vlogen-in-duitsland-over-parlementsgebouw-en-marinebasis
A9: Ireland | B9: https://www.irishexaminer.com/news/arid-41763413.html

Sheet ChangeLog
A1: 45725
A2: 2024 | B2: August | C2: Yes | D2: 45505 | E2: Unknown | F2: Drone overflights of industrial & military sites in Germany, suspected sabotage prep (Brunsbruttel) | G2: Germany | H2: Sabotage (preparation) | I2: Does not apply | J2: Degrade military infrastructure | K2: Inflict economic damage | L2: Military / weapons production infrastructure | M2: Energy / communications infrastructure | N2: No | O2: Excluded after December 2024 report that investigation had not revealed espionage link
A4: 45758
A5: ordered data by year and month
A7: 45819
A8: DisposableAgentsInvolved category added. First step in identifying who these individuals are.
A10: 45824
A11: Excluded cases organized by year & month of alleged incident, country.
A13: 45854
A14: Excluded the Leonid Volkov assault/assassination attempt because this appears part of longer-standing Russian attacks on political opposition abroad, rather than something directly linked to the war in Ukraine or Europe's support for Ukraine
A16: 45856
A17: Included two 'sticker' operations that only came to light through in-depth reporting on the Red Hands in paris case (2024). No references found to this elsewhere, but seems correct to include this nonetheless given detail of reporting. See: https://www.mediapart.fr/en/journal/international/090125/operation-red-hands-france-neo-nazi-agents-provocateurs-kremlins-pay
A19: 45924
A20: The suspected arson at Diehl Metall factory used for weapons production as been excluded. In December 2024, the prosecutor handling the case ruled out sabotage.
